[{"vehicle_update_ts": 1718233313, "lat": 39.63085174560547, "lon": -104.90511322021484, "trip": "114913677", "route_id": "AT", "stop_id": "26198", "vehicle_id": "1A5C9CB68FBE9B34E063DD4D1FACBFC2", "vehicle_label": "1505"}, {"vehicle_update_ts": 1718233318, "lat": 39.59716796875, "lon": -104.8863525390625, "trip": "114916312", "route_id": "P", "stop_id": "34433", "vehicle_id": "1A5C9CB68FC59B34E063DD4D1FACBFC2", "vehicle_label": "1501"}, {"vehicle_update_ts": 1718233308, "lat": 39.64251708984375, "lon": -104.87918090820312, "trip": "114913697", "route_id": "AT", "stop_id": "19074", "vehicle_id": "1A5C9CB68FCD9B34E063DD4D1FACBFC2", "vehicle_label": "1517"}, {"vehicle_update_ts": 1718233224, "lat": 39.838401794433594, "lon": -104.66960144042969, "trip": "114913691", "route_id": "AT", "stop_id": "22924", "vehicle_id": "1A5C9CB68FCE9B34E063DD4D1FACBFC2", "vehicle_label": "1518"}, {"vehicle_update_ts": 1718233314, "lat": 40.00546646118164, "lon": -105.27168273925781, "trip": "114913532", "route_id": "AB1", "stop_id": "12433", "vehicle_id": "1A5C9CB68FE49B34E063DD4D1FACBFC2", "vehicle_label": "1540"}, {"vehicle_update_ts": 1718233299, "lat": 39.88501739501953, "lon": -104.94204711914062, "trip": "114899518", "route_id": "104L", "stop_id": "23718", "vehicle_id": "1A5C9CB68FE99B34E063DD4D1FACBFC2", "vehicle_label": "1545"}, {"vehicle_update_ts": 1718233326, "lat": 39.74381637573242, "lon": -104.99313354492188, "trip": "114923563", "route_id": "MALL", "stop_id": "35435", "vehicle_id": "1A5C9CB68FF89B34E063DD4D1FACBFC2", "vehicle_label": "1656"}, {"vehicle_update_ts": 1718233322, "lat": 39.754981994628906, "lon": -105.00323486328125, "trip": "114923564", "route_id": "MALL", "stop_id": "33646", "vehicle_id": "1A5C9CB68FFC9B34E063DD4D1FACBFC2", "vehicle_label": "1660"}, {"vehicle_update_ts": 1718233313, "lat": 39.74773406982422, "lon": -104.99313354492188, "trip": "114923449", "route_id": "MALL", "stop_id": "35419", "vehicle_id": "1A5C9CB690149B34E063DD4D1FACBFC2", "vehicle_label": "1684"}, {"vehicle_update_ts": 1718233311, "lat": 39.7515983581543, "lon": -104.9934310913086, "trip": "114922728", "route_id": "FMR", "stop_id": "34297", "vehicle_id": "1A5C9CB690179B34E063DD4D1FACBFC2", "vehicle_label": "1801"}, {"vehicle_update_ts": 1718233300, "lat": 39.74718475341797, "lon": -104.99005126953125, "trip": "114922656", "route_id": "FMR", "stop_id": "34304", "vehicle_id": "1A5C9CB6901B9B34E063DD4D1FACBFC2", "vehicle_label": "1805"}, {"vehicle_update_ts": 1718233302, "lat": 39.75529861450195, "lon": -105.00250244140625, "trip": "114922654", "route_id": "FMR", "stop_id": "34310", "vehicle_id": "1A5C9CB6901C9B34E063DD4D1FACBFC2", "vehicle_label": "1806"}, {"vehicle_update_ts": 1718232902, "lat": 39.7551155090332, "lon": -105.00250244140625, "trip": "114922653", "route_id": "FMR", "stop_id": "34310", "vehicle_id": "1A5C9CB6901D9B34E063DD4D1FACBFC2", "vehicle_label": "1807"}, {"vehicle_update_ts": 1718233147, "lat": 39.74053192138672, "lon": -104.98690032958984, "trip": "114922727", "route_id": "FMR", "stop_id": "35037", "vehicle_id": "1A5C9CB690209B34E063DD4D1FACBFC2", "vehicle_label": "1810"}, {"vehicle_update_ts": 1718233306, "lat": 39.6967658996582, "lon": -104.93413543701172, "trip": "114910027", "route_id": "46", "stop_id": "12757", "vehicle_id": "1A5C9CB690259B34E063DD4D1FACBFC2", "vehicle_label": "3003"}, {"vehicle_update_ts": 1718233315, "lat": 39.67991638183594, "lon": -104.93863677978516, "trip": "114910003", "route_id": "46", "stop_id": "26121", "vehicle_id": "1A5C9CB690289B34E063DD4D1FACBFC2", "vehicle_label": "3006"}, {"vehicle_update_ts": 1718233312, "lat": 39.54249954223633, "lon": -104.93222045898438, "trip": "114908870", "route_id": "402L", "stop_id": "23851", "vehicle_id": "1A5C9CB690299B34E063DD4D1FACBFC2", "vehicle_label": "3007"}, {"vehicle_update_ts": 1718233303, "lat": 39.65311813354492, "lon": -104.91203308105469, "trip": "114910026", "route_id": "46", "stop_id": "15540", "vehicle_id": "1A5C9CB6902A9B34E063DD4D1FACBFC2", "vehicle_label": "3008"}, {"vehicle_update_ts": 1718233308, "lat": 39.5463981628418, "lon": -104.97821807861328, "trip": "114908884", "route_id": "402L", "stop_id": "24964", "vehicle_id": "1A5C9CB6902C9B34E063DD4D1FACBFC2", "vehicle_label": "3010"}, {"vehicle_update_ts": 1718233318, "lat": 39.71649932861328, "lon": -104.94866943359375, "trip": "114910002", "route_id": "46", "stop_id": "25338", "vehicle_id": "1A5C9CB6902D9B34E063DD4D1FACBFC2", "vehicle_label": "3011"}, {"vehicle_update_ts": 1718233311, "lat": 40.17205047607422, "lon": -105.10848236083984, "trip": "114907804", "route_id": "324", "stop_id": "35484", "vehicle_id": "1A5C9CB6902E9B34E063DD4D1FACBFC2", "vehicle_label": "3012"}, {"vehicle_update_ts": 1718233308, "lat": 40.15195083618164, "lon": -105.1024169921875, "trip": "114907752", "route_id": "324", "stop_id": "15166", "vehicle_id": "1A5C9CB690309B34E063DD4D1FACBFC2", "vehicle_label": "3014"}, {"vehicle_update_ts": 1718233314, "lat": 40.17228317260742, "lon": -105.10846710205078, "trip": "114907874", "route_id": "326", "stop_id": "35484", "vehicle_id": "1A5C9CB690329B34E063DD4D1FACBFC2", "vehicle_label": "3016"}, {"vehicle_update_ts": 1718233306, "lat": 40.1510009765625, "lon": -105.13079833984375, "trip": "114907694", "route_id": "323", "stop_id": "34665", "vehicle_id": "1A5C9CB690369B34E063DD4D1FACBFC2", "vehicle_label": "3020"}, {"vehicle_update_ts": 1718233320, "lat": 40.144168853759766, "lon": -105.132080078125, "trip": "114907803", "route_id": "324", "stop_id": "25675", "vehicle_id": "1A5C9CB690389B34E063DD4D1FACBFC2", "vehicle_label": "3022"}, {"vehicle_update_ts": 1718233317, "lat": 40.01734924316406, "lon": -105.27648162841797, "trip": "114921050", "route_id": "FF1", "stop_id": "18977", "vehicle_id": "1A5C9CB6903D9B34E063DD4D1FACBFC2", "vehicle_label": "3602"}, {"vehicle_update_ts": 1718233312, "lat": 39.95893478393555, "lon": -105.16706848144531, "trip": "114913541", "route_id": "AB1", "stop_id": "34656", "vehicle_id": "1A5C9CB6903E9B34E063DD4D1FACBFC2", "vehicle_label": "3603"}, {"vehicle_update_ts": 1718233316, "lat": 40.09356689453125, "lon": -105.18608093261719, "trip": "114913841", "route_id": "BOLT", "stop_id": "18107", "vehicle_id": "1A5C9CB690409B34E063DD4D1FACBFC2", "vehicle_label": "3605"}, {"vehicle_update_ts": 1718233300, "lat": 39.76276779174805, "lon": -104.99508666992188, "trip": "114921055", "route_id": "FF1", "stop_id": "23955", "vehicle_id": "1A5C9CB690429B34E063DD4D1FACBFC2", "vehicle_label": "3607"}, {"vehicle_update_ts": 1718233320, "lat": 39.828548431396484, "lon": -104.99835205078125, "trip": "114914651", "route_id": "FF1", "stop_id": "22903", "vehicle_id": "1A5C9CB690439B34E063DD4D1FACBFC2", "vehicle_label": "3608"}, {"vehicle_update_ts": 1718233315, "lat": 39.759883880615234, "lon": -104.99455261230469, "trip": "114921054", "route_id": "FF1", "stop_id": "23955", "vehicle_id": "1A5C9CB690479B34E063DD4D1FACBFC2", "vehicle_label": "3612"}, {"vehicle_update_ts": 1718233320, "lat": 40.17155075073242, "lon": -105.10845184326172, "trip": "114913854", "route_id": "BOLT", "stop_id": "35487", "vehicle_id": "1A5C9CB690499B34E063DD4D1FACBFC2", "vehicle_label": "3614"}, {"vehicle_update_ts": 1718233312, "lat": 40.01715087890625, "lon": -105.2763671875, "trip": "114914722", "route_id": "GS", "stop_id": "26100", "vehicle_id": "1A5C9CB6904C9B34E063DD4D1FACBFC2", "vehicle_label": "3617"}, {"vehicle_update_ts": 1718233303, "lat": 39.98528289794922, "lon": -105.2320327758789, "trip": "114913519", "route_id": "AB1", "stop_id": "34655", "vehicle_id": "1A5C9CB690539B34E063DD4D1FACBFC2", "vehicle_label": "3624"}, {"vehicle_update_ts": 1718233299, "lat": 39.986698150634766, "lon": -105.23242950439453, "trip": "114914652", "route_id": "FF1", "stop_id": "12604", "vehicle_id": "1A5C9CB690579B34E063DD4D1FACBFC2", "vehicle_label": "3628"}, {"vehicle_update_ts": 1718233323, "lat": 39.91583251953125, "lon": -104.85611724853516, "trip": "114916393", "route_id": "RX", "stop_id": "19159", "vehicle_id": "1A5C9CB690589B34E063DD4D1FACBFC2", "vehicle_label": "3629"}, {"vehicle_update_ts": 1718233319, "lat": 39.92485046386719, "lon": -105.11178588867188, "trip": "114921053", "route_id": "FF1", "stop_id": "33535", "vehicle_id": "1A5C9CB690629B34E063DD4D1FACBFC2", "vehicle_label": "3641"}, {"vehicle_update_ts": 1718233318, "lat": 39.853084564208984, "lon": -105.05066680908203, "trip": "114921033", "route_id": "FF2", "stop_id": "23955", "vehicle_id": "1A5C9CB690649B34E063DD4D1FACBFC2", "vehicle_label": "3639"}, {"vehicle_update_ts": 1718233313, "lat": 39.82773208618164, "lon": -104.98733520507812, "trip": "114914628", "route_id": "FF5", "stop_id": "22903", "vehicle_id": "1A5C9CB690689B34E063DD4D1FACBFC2", "vehicle_label": "3645"}, {"vehicle_update_ts": 1718233311, "lat": 39.83788299560547, "lon": -104.67611694335938, "trip": "114899517", "route_id": "104L", "stop_id": "33803", "vehicle_id": "1A5C9CB6906A9B34E063DD4D1FACBFC2", "vehicle_label": "3647"}, {"vehicle_update_ts": 1718233308, "lat": 39.68669891357422, "lon": -105.18806457519531, "trip": "114914135", "route_id": "CV", "stop_id": "24435", "vehicle_id": "1A5C9CB6906D9B34E063DD4D1FACBFC2", "vehicle_label": "3650"}, {"vehicle_update_ts": 1718233304, "lat": 39.910465240478516, "lon": -105.08757019042969, "trip": "114914670", "route_id": "FF1", "stop_id": "25332", "vehicle_id": "1A5C9CB6906F9B34E063DD4D1FACBFC2", "vehicle_label": "3652"}, {"vehicle_update_ts": 1718233306, "lat": 39.68024826049805, "lon": -105.36371612548828, "trip": "114914362", "route_id": "EV", "stop_id": "20338", "vehicle_id": "1A5C9CB690769B34E063DD4D1FACBFC2", "vehicle_label": "3661"}, {"vehicle_update_ts": 1718233306, "lat": 39.960533142089844, "lon": -105.17218017578125, "trip": "114914625", "route_id": "FF2", "stop_id": "17891", "vehicle_id": "1A5C9CB690779B34E063DD4D1FACBFC2", "vehicle_label": "3662"}, {"vehicle_update_ts": 1718233299, "lat": 39.72549819946289, "lon": -105.12135314941406, "trip": "114901414", "route_id": "116X", "stop_id": "33656", "vehicle_id": "1A5C9CB6907E9B34E063DD4D1FACBFC2", "vehicle_label": "3669"}, {"vehicle_update_ts": 1718233326, "lat": 40.04203414916992, "lon": -105.24114990234375, "trip": "114913821", "route_id": "BOLT", "stop_id": "17994", "vehicle_id": "1A5C9CB690869B34E063DD4D1FACBFC2", "vehicle_label": "3703"}, {"vehicle_update_ts": 1718233309, "lat": 40.01210021972656, "lon": -105.27771759033203, "trip": "114914653", "route_id": "FF1", "stop_id": "99850", "vehicle_id": "1A5C9CB690879B34E063DD4D1FACBFC2", "vehicle_label": "3704"}, {"vehicle_update_ts": 1718233318, "lat": 40.19948196411133, "lon": -105.10416412353516, "trip": "114913807", "route_id": "BOLT", "stop_id": "33774", "vehicle_id": "1A5C9CB690899B34E063DD4D1FACBFC2", "vehicle_label": "3706"}, {"vehicle_update_ts": 1718233323, "lat": 39.9768180847168, "lon": -105.21393585205078, "trip": "114921052", "route_id": "FF1", "stop_id": "19775", "vehicle_id": "1A5C9CB6908C9B34E063DD4D1FACBFC2", "vehicle_label": "3709"}, {"vehicle_update_ts": 1718233315, "lat": 39.98576736450195, "lon": -105.2479476928711, "trip": "114921051", "route_id": "FF1", "stop_id": "16680", "vehicle_id": "1A5C9CB6908F9B34E063DD4D1FACBFC2", "vehicle_label": "3712"}, {"vehicle_update_ts": 1718233317, "lat": 40.000267028808594, "lon": -105.09725189208984, "trip": "114915005", "route_id": "LD1", "stop_id": "19963", "vehicle_id": "1A5C9CB690909B34E063DD4D1FACBFC2", "vehicle_label": "3713"}, {"vehicle_update_ts": 1718233311, "lat": 39.75014877319336, "lon": -104.98881530761719, "trip": "114916392", "route_id": "RX", "stop_id": "10550", "vehicle_id": "1A5C9CB690919B34E063DD4D1FACBFC2", "vehicle_label": "3714"}, {"vehicle_update_ts": 1718233316, "lat": 39.73236846923828, "lon": -105.16549682617188, "trip": "114914727", "route_id": "GS", "stop_id": "24158", "vehicle_id": "1A5C9CB690979B34E063DD4D1FACBFC2", "vehicle_label": "3720"}, {"vehicle_update_ts": 1718233300, "lat": 40.01701736450195, "lon": -105.279052734375, "trip": "114919280", "route_id": "NB3", "stop_id": "26102", "vehicle_id": "1A5C9CB6909C9B34E063DD4D1FACBFC2", "vehicle_label": "3725"}, {"vehicle_update_ts": 1718233307, "lat": 39.8852653503418, "lon": -104.89624786376953, "trip": "114899503", "route_id": "104L", "stop_id": "33267", "vehicle_id": "1A5C9CB690A59B34E063DD4D1FACBFC2", "vehicle_label": "3734"}, {"vehicle_update_ts": 1718233316, "lat": 39.757816314697266, "lon": -105.01101684570312, "trip": "114906742", "route_id": "28", "stop_id": "10254", "vehicle_id": "1A5C9CB690C39B34E063DD4D1FACBFC2", "vehicle_label": "6004"}, {"vehicle_update_ts": 1718233303, "lat": 39.773582458496094, "lon": -104.87711334228516, "trip": "114908170", "route_id": "37", "stop_id": "34400", "vehicle_id": "1A5C9CB690C49B34E063DD4D1FACBFC2", "vehicle_label": "6005"}, {"vehicle_update_ts": 1718233323, "lat": 39.91398239135742, "lon": -104.9538345336914, "trip": "114902172", "route_id": "120L", "stop_id": "35275", "vehicle_id": "1A5C9CB690C69B34E063DD4D1FACBFC2", "vehicle_label": "6007"}, {"vehicle_update_ts": 1718233278, "lat": 39.66365051269531, "lon": -104.98766326904297, "trip": "", "route_id": "", "stop_id": "", "vehicle_id": "1A5C9CB690C89B34E063DD4D1FACBFC2", "vehicle_label": "6009"}, {"vehicle_update_ts": 1718233322, "lat": 39.74486541748047, "lon": -104.97386932373047, "trip": "114905703", "route_id": "20", "stop_id": "10338", "vehicle_id": "1A5C9CB690C99B34E063DD4D1FACBFC2", "vehicle_label": "6010"}, {"vehicle_update_ts": 1718233315, "lat": 39.758399963378906, "lon": -104.90995025634766, "trip": "114906734", "route_id": "28", "stop_id": "19054", "vehicle_id": "1A5C9CB690CA9B34E063DD4D1FACBFC2", "vehicle_label": "6011"}, {"vehicle_update_ts": 1718233320, "lat": 39.74041748046875, "lon": -105.03350067138672, "trip": "114904985", "route_id": "16", "stop_id": "12915", "vehicle_id": "1A5C9CB690CB9B34E063DD4D1FACBFC2", "vehicle_label": "6012"}, {"vehicle_update_ts": 1718233307, "lat": 39.74021530151367, "lon": -105.07696533203125, "trip": "114904918", "route_id": "16", "stop_id": "12987", "vehicle_id": "1A5C9CB690CE9B34E063DD4D1FACBFC2", "vehicle_label": "6015"}, {"vehicle_update_ts": 1718233326, "lat": 39.78499984741211, "lon": -104.94978332519531, "trip": "114910184", "route_id": "48", "stop_id": "16654", "vehicle_id": "1A5C9CB690CF9B34E063DD4D1FACBFC2", "vehicle_label": "6016"}, {"vehicle_update_ts": 1718233315, "lat": 39.76184844970703, "lon": -104.9325180053711, "trip": "114909445", "route_id": "43", "stop_id": "15228", "vehicle_id": "1A5C9CB690D09B34E063DD4D1FACBFC2", "vehicle_label": "6017"}, {"vehicle_update_ts": 1718233326, "lat": 39.69654846191406, "lon": -104.95866394042969, "trip": "114900797", "route_id": "11", "stop_id": "15347", "vehicle_id": "1A5C9CB690D19B34E063DD4D1FACBFC2", "vehicle_label": "6018"}, {"vehicle_update_ts": 1718233308, "lat": 39.73991775512695, "lon": -105.19740295410156, "trip": "114905329", "route_id": "17", "stop_id": "35480", "vehicle_id": "1A5C9CB690D39B34E063DD4D1FACBFC2", "vehicle_label": "6020"}, {"vehicle_update_ts": 1718233311, "lat": 39.718631744384766, "lon": -105.1323471069336, "trip": "114905395", "route_id": "17", "stop_id": "33665", "vehicle_id": "1A5C9CB690D59B34E063DD4D1FACBFC2", "vehicle_label": "6022"}, {"vehicle_update_ts": 1718233326, "lat": 39.74024963378906, "lon": -104.99960327148438, "trip": "114904984", "route_id": "16", "stop_id": "18982", "vehicle_id": "1A5C9CB690D69B34E063DD4D1FACBFC2", "vehicle_label": "6023"}, {"vehicle_update_ts": 1718233306, "lat": 39.762001037597656, "lon": -104.9627685546875, "trip": "114909521", "route_id": "43", "stop_id": "15257", "vehicle_id": "1A5C9CB690D89B34E063DD4D1FACBFC2", "vehicle_label": "6025"}, {"vehicle_update_ts": 1718233318, "lat": 39.7039680480957, "lon": -105.00191497802734, "trip": "114900784", "route_id": "11", "stop_id": "24392", "vehicle_id": "1A5C9CB690DB9B34E063DD4D1FACBFC2", "vehicle_label": "6028"}, {"vehicle_update_ts": 1718233305, "lat": 39.72629928588867, "lon": -105.12953186035156, "trip": "114905331", "route_id": "17", "stop_id": "16775", "vehicle_id": "1A5C9CB690DD9B34E063DD4D1FACBFC2", "vehicle_label": "6030"}, {"vehicle_update_ts": 1718233322, "lat": 39.76966857910156, "lon": -105.00170135498047, "trip": "114905515", "route_id": "19", "stop_id": "14990", "vehicle_id": "1A5C9CB690DE9B34E063DD4D1FACBFC2", "vehicle_label": "6031"}, {"vehicle_update_ts": 1718233311, "lat": 39.740318298339844, "lon": -105.10486602783203, "trip": "114904986", "route_id": "16", "stop_id": "25789", "vehicle_id": "1A5C9CB690DF9B34E063DD4D1FACBFC2", "vehicle_label": "6032"}, {"vehicle_update_ts": 1718233319, "lat": 40.017417907714844, "lon": -105.27667999267578, "trip": "114905804", "route_id": "204", "stop_id": "19825", "vehicle_id": "1A5C9CB690E39B34E063DD4D1FACBFC2", "vehicle_label": "6036"}, {"vehicle_update_ts": 1718233320, "lat": 39.74553298950195, "lon": -105.00350189208984, "trip": "114909541", "route_id": "43", "stop_id": "34970", "vehicle_id": "1A5C9CB690E59B34E063DD4D1FACBFC2", "vehicle_label": "6038"}, {"vehicle_update_ts": 1718233323, "lat": 39.762081146240234, "lon": -105.08087921142578, "trip": "114907646", "route_id": "32", "stop_id": "10923", "vehicle_id": "1A5C9CB690E79B34E063DD4D1FACBFC2", "vehicle_label": "6040"}, {"vehicle_update_ts": 1718233313, "lat": 39.7401008605957, "lon": -105.1146011352539, "trip": "114904917", "route_id": "16", "stop_id": "12918", "vehicle_id": "1A5C9CB690E99B34E063DD4D1FACBFC2", "vehicle_label": "6042"}, {"vehicle_update_ts": 1718233317, "lat": 39.757850646972656, "lon": -105.0098648071289, "trip": "114907640", "route_id": "32", "stop_id": "22575", "vehicle_id": "1A5C9CB690EA9B34E063DD4D1FACBFC2", "vehicle_label": "6043"}, {"vehicle_update_ts": 1718233313, "lat": 39.77311706542969, "lon": -104.8057861328125, "trip": "114909130", "route_id": "42", "stop_id": "25480", "vehicle_id": "1A5C9CB690ED9B34E063DD4D1FACBFC2", "vehicle_label": "6047"}, {"vehicle_update_ts": 1718232980, "lat": 39.657981872558594, "lon": -104.84603118896484, "trip": "", "route_id": "", "stop_id": "", "vehicle_id": "1A5C9CB690EE9B34E063DD4D1FACBFC2", "vehicle_label": "6048"}, {"vehicle_update_ts": 1718233314, "lat": 39.79035186767578, "lon": -104.80716705322266, "trip": "114909893", "route_id": "45", "stop_id": "20870", "vehicle_id": "1A5C9CB690F19B34E063DD4D1FACBFC2", "vehicle_label": "6051"}, {"vehicle_update_ts": 1718233298, "lat": 39.682151794433594, "lon": -105.08418273925781, "trip": "114906262", "route_id": "21", "stop_id": "14693", "vehicle_id": "1A5C9CB690F29B34E063DD4D1FACBFC2", "vehicle_label": "6052"}, {"vehicle_update_ts": 1718233306, "lat": 39.772884368896484, "lon": -104.94084930419922, "trip": "114908162", "route_id": "37", "stop_id": "13071", "vehicle_id": "1A5C9CB690F49B34E063DD4D1FACBFC2", "vehicle_label": "6054"}, {"vehicle_update_ts": 1718233302, "lat": 39.75790023803711, "lon": -104.99897003173828, "trip": "114905571", "route_id": "19", "stop_id": "23400", "vehicle_id": "1A5C9CB690F59B34E063DD4D1FACBFC2", "vehicle_label": "6055"}, {"vehicle_update_ts": 1718233315, "lat": 39.760433197021484, "lon": -104.89080047607422, "trip": "114899912", "route_id": "105", "stop_id": "26071", "vehicle_id": "1A5C9CB690F79B34E063DD4D1FACBFC2", "vehicle_label": "6057"}, {"vehicle_update_ts": 1718233317, "lat": 39.60008239746094, "lon": -104.71186828613281, "trip": "114903177", "route_id": "135", "stop_id": "33324", "vehicle_id": "1A5C9CB690F99B34E063DD4D1FACBFC2", "vehicle_label": "6059"}, {"vehicle_update_ts": 1718233300, "lat": 39.73518371582031, "lon": -104.97366333007812, "trip": "114896620", "route_id": "10", "stop_id": "10187", "vehicle_id": "1A5C9CB690FA9B34E063DD4D1FACBFC2", "vehicle_label": "6060"}, {"vehicle_update_ts": 1718233320, "lat": 39.69243240356445, "lon": -104.8100357055664, "trip": "114904178", "route_id": "153", "stop_id": "12708", "vehicle_id": "1A5C9CB690FB9B34E063DD4D1FACBFC2", "vehicle_label": "6061"}, {"vehicle_update_ts": 1718233308, "lat": 39.652984619140625, "lon": -104.88361358642578, "trip": "114899795", "route_id": "105", "stop_id": "14131", "vehicle_id": "1A5C9CB690FC9B34E063DD4D1FACBFC2", "vehicle_label": "6062"}, {"vehicle_update_ts": 1718233326, "lat": 39.74013137817383, "lon": -104.95918273925781, "trip": "114903955", "route_id": "15", "stop_id": "12898", "vehicle_id": "1A5C9CB691009B34E063DD4D1FACBFC2", "vehicle_label": "6066"}, {"vehicle_update_ts": 1718233307, "lat": 39.7675666809082, "lon": -104.78273010253906, "trip": "114909892", "route_id": "45", "stop_id": "26156", "vehicle_id": "1A5C9CB691049B34E063DD4D1FACBFC2", "vehicle_label": "6070"}, {"vehicle_update_ts": 1718233306, "lat": 39.59709930419922, "lon": -104.88096618652344, "trip": "114904146", "route_id": "153", "stop_id": "23200", "vehicle_id": "1A5C9CB691069B34E063DD4D1FACBFC2", "vehicle_label": "6074"}, {"vehicle_update_ts": 1718233304, "lat": 39.7674674987793, "lon": -104.90208435058594, "trip": "114908175", "route_id": "37", "stop_id": "33594", "vehicle_id": "1A5C9CB691079B34E063DD4D1FACBFC2", "vehicle_label": "6075"}, {"vehicle_update_ts": 1718233323, "lat": 39.74131774902344, "lon": -104.75240325927734, "trip": "114903834", "route_id": "15", "stop_id": "14311", "vehicle_id": "1A5C9CB691089B34E063DD4D1FACBFC2", "vehicle_label": "6076"}, {"vehicle_update_ts": 1718233098, "lat": 39.74021530151367, "lon": -104.93765258789062, "trip": "", "route_id": "", "stop_id": "", "vehicle_id": "1A5C9CB6910B9B34E063DD4D1FACBFC2", "vehicle_label": "6079"}, {"vehicle_update_ts": 1718233314, "lat": 39.77294921875, "lon": -104.80123138427734, "trip": "114902659", "route_id": "121", "stop_id": "25696", "vehicle_id": "1A5C9CB6910C9B34E063DD4D1FACBFC2", "vehicle_label": "6080"}, {"vehicle_update_ts": 1718233322, "lat": 39.74748229980469, "lon": -104.88291931152344, "trip": "114905709", "route_id": "20", "stop_id": "15609", "vehicle_id": "1A5C9CB6910D9B34E063DD4D1FACBFC2", "vehicle_label": "6081"}, {"vehicle_update_ts": 1718233326, "lat": 39.74751663208008, "lon": -104.8750991821289, "trip": "114899812", "route_id": "105", "stop_id": "15578", "vehicle_id": "1A5C9CB6910E9B34E063DD4D1FACBFC2", "vehicle_label": "6082"}, {"vehicle_update_ts": 1718233309, "lat": 39.654415130615234, "lon": -104.86730194091797, "trip": "114899855", "route_id": "105", "stop_id": "14148", "vehicle_id": "1A5C9CB6910F9B34E063DD4D1FACBFC2", "vehicle_label": "6083"}, {"vehicle_update_ts": 1718233322, "lat": 39.77473449707031, "lon": -104.75309753417969, "trip": "114909118", "route_id": "42", "stop_id": "33437", "vehicle_id": "1A5C9CB691109B34E063DD4D1FACBFC2", "vehicle_label": "6084"}, {"vehicle_update_ts": 1718233301, "lat": 39.59505081176758, "lon": -104.79865264892578, "trip": "114904169", "route_id": "153", "stop_id": "19774", "vehicle_id": "1A5C9CB691119B34E063DD4D1FACBFC2", "vehicle_label": "6085"}, {"vehicle_update_ts": 1718233278, "lat": 39.70561599731445, "lon": -104.84728240966797, "trip": "114902661", "route_id": "121", "stop_id": "33678", "vehicle_id": "1A5C9CB691139B34E063DD4D1FACBFC2", "vehicle_label": "6087"}, {"vehicle_update_ts": 1718233322, "lat": 39.73283386230469, "lon": -104.87491607666016, "trip": "114896583", "route_id": "10", "stop_id": "10102", "vehicle_id": "1A5C9CB691159B34E063DD4D1FACBFC2", "vehicle_label": "6089"}, {"vehicle_update_ts": 1718233326, "lat": 39.838233947753906, "lon": -104.66967010498047, "trip": "114905185", "route_id": "169L", "stop_id": "22924", "vehicle_id": "1A5C9CB691169B34E063DD4D1FACBFC2", "vehicle_label": "6090"}, {"vehicle_update_ts": 1718233320, "lat": 39.74039840698242, "lon": -104.83854675292969, "trip": "114903928", "route_id": "15", "stop_id": "12995", "vehicle_id": "1A5C9CB691179B34E063DD4D1FACBFC2", "vehicle_label": "6091"}, {"vehicle_update_ts": 1718233299, "lat": 39.7328987121582, "lon": -104.88048553466797, "trip": "114896619", "route_id": "10", "stop_id": "25270", "vehicle_id": "1A5C9CB691189B34E063DD4D1FACBFC2", "vehicle_label": "6092"}, {"vehicle_update_ts": 1718233322, "lat": 39.594818115234375, "lon": -104.811767578125, "trip": "114904136", "route_id": "153", "stop_id": "33362", "vehicle_id": "1A5C9CB691199B34E063DD4D1FACBFC2", "vehicle_label": "6093"}, {"vehicle_update_ts": 1718233326, "lat": 39.65986633300781, "lon": -104.79098510742188, "trip": "114905128", "route_id": "169", "stop_id": "18951", "vehicle_id": "1A5C9CB6911C9B34E063DD4D1FACBFC2", "vehicle_label": "6096"}, {"vehicle_update_ts": 1718233306, "lat": 39.7457160949707, "lon": -104.9906005859375, "trip": "114905656", "route_id": "20", "stop_id": "17711", "vehicle_id": "1A5C9CB6911F9B34E063DD4D1FACBFC2", "vehicle_label": "6099"}, {"vehicle_update_ts": 1718233322, "lat": 39.78105163574219, "lon": -104.75917053222656, "trip": "114909125", "route_id": "42", "stop_id": "19660", "vehicle_id": "1A5C9CB691209B34E063DD4D1FACBFC2", "vehicle_label": "6100"}, {"vehicle_update_ts": 1718233299, "lat": 39.75148391723633, "lon": -104.99797058105469, "trip": "114903796", "route_id": "15", "stop_id": "20745", "vehicle_id": "1A5C9CB691219B34E063DD4D1FACBFC2", "vehicle_label": "6101"}, {"vehicle_update_ts": 1718233317, "lat": 39.74006652832031, "lon": -104.94041442871094, "trip": "114903778", "route_id": "15", "stop_id": "12845", "vehicle_id": "1A5C9CB691249B34E063DD4D1FACBFC2", "vehicle_label": "6104"}, {"vehicle_update_ts": 1718233311, "lat": 39.76413345336914, "lon": -104.85299682617188, "trip": "114902549", "route_id": "121", "stop_id": "23518", "vehicle_id": "1A5C9CB691259B34E063DD4D1FACBFC2", "vehicle_label": "6105"}, {"vehicle_update_ts": 1718233314, "lat": 39.78084945678711, "lon": -104.84691619873047, "trip": "114909848", "route_id": "45", "stop_id": "34715", "vehicle_id": "1A5C9CB691269B34E063DD4D1FACBFC2", "vehicle_label": "6106"}, {"vehicle_update_ts": 1718233299, "lat": 39.73716735839844, "lon": -104.8235855102539, "trip": "", "route_id": "", "stop_id": "", "vehicle_id": "1A5C9CB691279B34E063DD4D1FACBFC2", "vehicle_label": "6107"}, {"vehicle_update_ts": 1718233326, "lat": 39.709232330322266, "lon": -104.81475067138672, "trip": "114904135", "route_id": "153", "stop_id": "11950", "vehicle_id": "1A5C9CB691289B34E063DD4D1FACBFC2", "vehicle_label": "6108"}, {"vehicle_update_ts": 1718233314, "lat": 39.75678253173828, "lon": -104.81932067871094, "trip": "114904198", "route_id": "153", "stop_id": "18751", "vehicle_id": "1A5C9CB691299B34E063DD4D1FACBFC2", "vehicle_label": "6109"}, {"vehicle_update_ts": 1718233305, "lat": 39.73991775512695, "lon": -104.88043212890625, "trip": "114903805", "route_id": "15", "stop_id": "12867", "vehicle_id": "1A5C9CB6912B9B34E063DD4D1FACBFC2", "vehicle_label": "6111"}, {"vehicle_update_ts": 1718233315, "lat": 39.73503112792969, "lon": -104.95948028564453, "trip": "114896582", "route_id": "10", "stop_id": "10190", "vehicle_id": "1A5C9CB6912E9B34E063DD4D1FACBFC2", "vehicle_label": "6114"}, {"vehicle_update_ts": 1718233324, "lat": 39.63861846923828, "lon": -104.8174819946289, "trip": "114903271", "route_id": "139", "stop_id": "16201", "vehicle_id": "1A5C9CB6912F9B34E063DD4D1FACBFC2", "vehicle_label": "6115"}, {"vehicle_update_ts": 1718233309, "lat": 39.778831481933594, "lon": -104.84712982177734, "trip": "114902641", "route_id": "121", "stop_id": "15906", "vehicle_id": "1A5C9CB691309B34E063DD4D1FACBFC2", "vehicle_label": "6116"}, {"vehicle_update_ts": 1718233315, "lat": 39.74323272705078, "lon": -105.01260375976562, "trip": "114896408", "route_id": "1", "stop_id": "10224", "vehicle_id": "1A5C9CB691319B34E063DD4D1FACBFC2", "vehicle_label": "6117"}, {"vehicle_update_ts": 1718233324, "lat": 39.75484848022461, "lon": -105.03703308105469, "trip": "114906724", "route_id": "28", "stop_id": "34717", "vehicle_id": "1A5C9CB691E39B34E063DD4D1FACBFC2", "vehicle_label": "6124"}, {"vehicle_update_ts": 1718233311, "lat": 39.74108123779297, "lon": -104.98625183105469, "trip": "114910225", "route_id": "48", "stop_id": "35033", "vehicle_id": "1A5C9CB691E49B34E063DD4D1FACBFC2", "vehicle_label": "6125"}, {"vehicle_update_ts": 1718233305, "lat": 39.67841720581055, "lon": -104.9698486328125, "trip": "114906257", "route_id": "21", "stop_id": "13583", "vehicle_id": "1A5C9CB691ED9B34E063DD4D1FACBFC2", "vehicle_label": "6132"}, {"vehicle_update_ts": 1718233270, "lat": 39.719783782958984, "lon": -105.12930297851562, "trip": "114912738", "route_id": "99", "stop_id": "33652", "vehicle_id": "1A5C9CB691EE9B34E063DD4D1FACBFC2", "vehicle_label": "6133"}, {"vehicle_update_ts": 1718233320, "lat": 39.61808395385742, "lon": -104.81946563720703, "trip": "114910258", "route_id": "483", "stop_id": "25738", "vehicle_id": "1A5C9CB691F09B34E063DD4D1FACBFC2", "vehicle_label": "6135"}, {"vehicle_update_ts": 1718233307, "lat": 39.64899826049805, "lon": -105.02539825439453, "trip": "114906856", "route_id": "29", "stop_id": "13835", "vehicle_id": "1A5C9CB691F59B34E063DD4D1FACBFC2", "vehicle_label": "6140"}, {"vehicle_update_ts": 1718233306, "lat": 39.6926155090332, "lon": -105.025146484375, "trip": "114907513", "route_id": "31", "stop_id": "13814", "vehicle_id": "1A5C9CB691F79B34E063DD4D1FACBFC2", "vehicle_label": "6142"}, {"vehicle_update_ts": 1718233307, "lat": 39.61119842529297, "lon": -105.08309936523438, "trip": "", "route_id": "", "stop_id": "", "vehicle_id": "1A5C9CB691FA9B34E063DD4D1FACBFC2", "vehicle_label": "6145"}, {"vehicle_update_ts": 1718233300, "lat": 39.70029830932617, "lon": -105.02503204345703, "trip": "114907410", "route_id": "31", "stop_id": "13829", "vehicle_id": "1A5C9CB691FF9B34E063DD4D1FACBFC2", "vehicle_label": "6150"}, {"vehicle_update_ts": 1718233323, "lat": 39.65534973144531, "lon": -105.08148193359375, "trip": "114911852", "route_id": "76", "stop_id": "17055", "vehicle_id": "1A5C9CB692029B34E063DD4D1FACBFC2", "vehicle_label": "6153"}, {"vehicle_update_ts": 1718233295, "lat": 39.98853302001953, "lon": -105.08916473388672, "trip": "114918927", "route_id": "JUMP", "stop_id": "25903", "vehicle_id": "1A5C9CB692039B34E063DD4D1FACBFC2", "vehicle_label": "6154"}, {"vehicle_update_ts": 1718233322, "lat": 39.99998474121094, "lon": -105.26018524169922, "trip": "114905787", "route_id": "204", "stop_id": "12338", "vehicle_id": "1A5C9CB692049B34E063DD4D1FACBFC2", "vehicle_label": "6155"}, {"vehicle_update_ts": 1718233298, "lat": 40.01470184326172, "lon": -105.23178100585938, "trip": "114906032", "route_id": "206", "stop_id": "13505", "vehicle_id": "1A5C9CB692059B34E063DD4D1FACBFC2", "vehicle_label": "6156"}, {"vehicle_update_ts": 1718233306, "lat": 40.00526809692383, "lon": -105.27120208740234, "trip": "114905829", "route_id": "204", "stop_id": "12434", "vehicle_id": "1A5C9CB692079B34E063DD4D1FACBFC2", "vehicle_label": "6158"}, {"vehicle_update_ts": 1718233318, "lat": 39.76914978027344, "lon": -104.92231750488281, "trip": "114908343", "route_id": "38", "stop_id": "14326", "vehicle_id": "1A5C9CB6920B9B34E063DD4D1FACBFC2", "vehicle_label": "6162"}, {"vehicle_update_ts": 1718233303, "lat": 39.65321731567383, "lon": -104.95951843261719, "trip": "114906642", "route_id": "24", "stop_id": "16813", "vehicle_id": "1A5C9CB6920C9B34E063DD4D1FACBFC2", "vehicle_label": "6163"}, {"vehicle_update_ts": 1718233311, "lat": 39.74058151245117, "lon": -105.0815200805664, "trip": "114911861", "route_id": "76", "stop_id": "17037", "vehicle_id": "1A5C9CB6920E9B34E063DD4D1FACBFC2", "vehicle_label": "6165"}, {"vehicle_update_ts": 1718233211, "lat": 39.85856628417969, "lon": -104.95311737060547, "trip": "114912425", "route_id": "88L", "stop_id": "21936", "vehicle_id": "1A5C9CB692119B34E063DD4D1FACBFC2", "vehicle_label": "6168"}, {"vehicle_update_ts": 1718233306, "lat": 39.85506820678711, "lon": -104.98628234863281, "trip": "114912702", "route_id": "93L", "stop_id": "23103", "vehicle_id": "1A5C9CB692129B34E063DD4D1FACBFC2", "vehicle_label": "6169"}, {"vehicle_update_ts": 1718233305, "lat": 39.908267974853516, "lon": -105.09613037109375, "trip": "114911828", "route_id": "76", "stop_id": "14455", "vehicle_id": "1A5C9CB692149B34E063DD4D1FACBFC2", "vehicle_label": "6171"}, {"vehicle_update_ts": 1718233315, "lat": 39.805667877197266, "lon": -104.92890167236328, "trip": "114910352", "route_id": "49", "stop_id": "11489", "vehicle_id": "1A5C9CB692189B34E063DD4D1FACBFC2", "vehicle_label": "6175"}, {"vehicle_update_ts": 1718233275, "lat": 39.79853439331055, "lon": -105.08087921142578, "trip": "114911469", "route_id": "72", "stop_id": "34539", "vehicle_id": "1A5C9CB692199B34E063DD4D1FACBFC2", "vehicle_label": "6176"}, {"vehicle_update_ts": 1718233318, "lat": 39.827266693115234, "lon": -104.91490173339844, "trip": "114912317", "route_id": "88", "stop_id": "11671", "vehicle_id": "1A5C9CB6921C9B34E063DD4D1FACBFC2", "vehicle_label": "6179"}, {"vehicle_update_ts": 1718233322, "lat": 39.92886734008789, "lon": -104.94026947021484, "trip": "114912716", "route_id": "93L", "stop_id": "35282", "vehicle_id": "1A5C9CB6921E9B34E063DD4D1FACBFC2", "vehicle_label": "6181"}, {"vehicle_update_ts": 1718233300, "lat": 39.71116638183594, "lon": -104.99223327636719, "trip": "114907074", "route_id": "3", "stop_id": "26257", "vehicle_id": "1A5C9CB692239B34E063DD4D1FACBFC2", "vehicle_label": "6186"}, {"vehicle_update_ts": 1718233301, "lat": 39.80160140991211, "lon": -105.07649993896484, "trip": "114910696", "route_id": "52", "stop_id": "26008", "vehicle_id": "1A5C9CB692249B34E063DD4D1FACBFC2", "vehicle_label": "6187"}, {"vehicle_update_ts": 1718233284, "lat": 39.822898864746094, "lon": -105.10964965820312, "trip": "114896708", "route_id": "100", "stop_id": "14833", "vehicle_id": "1A5C9CB692269B34E063DD4D1FACBFC2", "vehicle_label": "6189"}, {"vehicle_update_ts": 1718233301, "lat": 39.80179977416992, "lon": -105.07649993896484, "trip": "114911803", "route_id": "76", "stop_id": "26008", "vehicle_id": "1A5C9CB692279B34E063DD4D1FACBFC2", "vehicle_label": "6190"}, {"vehicle_update_ts": 1718233320, "lat": 39.78459930419922, "lon": -104.88262939453125, "trip": "", "route_id": "", "stop_id": "", "vehicle_id": "1A5C9CB692289B34E063DD4D1FACBFC2", "vehicle_label": "6191"}, {"vehicle_update_ts": 1718233326, "lat": 39.80194854736328, "lon": -105.08601379394531, "trip": "114910660", "route_id": "52", "stop_id": "20827", "vehicle_id": "1A5C9CB692299B34E063DD4D1FACBFC2", "vehicle_label": "6192"}, {"vehicle_update_ts": 1718233322, "lat": 39.740081787109375, "lon": -104.8326187133789, "trip": "114903818", "route_id": "15", "stop_id": "13013", "vehicle_id": "1A5C9CB6922A9B34E063DD4D1FACBFC2", "vehicle_label": "6193"}, {"vehicle_update_ts": 1718233311, "lat": 39.7400016784668, "lon": -104.98632049560547, "trip": "114903768", "route_id": "15", "stop_id": "12849", "vehicle_id": "1A5C9CB6922C9B34E063DD4D1FACBFC2", "vehicle_label": "6195"}, {"vehicle_update_ts": 1718233304, "lat": 39.737548828125, "lon": -105.12062072753906, "trip": "114905330", "route_id": "17", "stop_id": "33962", "vehicle_id": "1A5C9CB6922E9B34E063DD4D1FACBFC2", "vehicle_label": "6197"}, {"vehicle_update_ts": 1718233318, "lat": 39.77655029296875, "lon": -105.05985260009766, "trip": "114909646", "route_id": "44", "stop_id": "11115", "vehicle_id": "1A5C9CB692309B34E063DD4D1FACBFC2", "vehicle_label": "6199"}, {"vehicle_update_ts": 1718233315, "lat": 39.72403335571289, "lon": -104.88349914550781, "trip": "114910981", "route_id": "6", "stop_id": "25228", "vehicle_id": "1A5C9CB692319B34E063DD4D1FACBFC2", "vehicle_label": "6200"}, {"vehicle_update_ts": 1718233320, "lat": 39.9015998840332, "lon": -104.95970153808594, "trip": "114911413", "route_id": "7", "stop_id": "23700", "vehicle_id": "1A5C9CB692329B34E063DD4D1FACBFC2", "vehicle_label": "6201"}, {"vehicle_update_ts": 1718233313, "lat": 39.72913360595703, "lon": -104.9791030883789, "trip": "114911000", "route_id": "6", "stop_id": "11873", "vehicle_id": "1A5C9CB692359B34E063DD4D1FACBFC2", "vehicle_label": "6206"}, {"vehicle_update_ts": 1718233309, "lat": 39.849998474121094, "lon": -105.0531005859375, "trip": "114910486", "route_id": "51", "stop_id": "16520", "vehicle_id": "1A5C9CB692399B34E063DD4D1FACBFC2", "vehicle_label": "6208"}, {"vehicle_update_ts": 1718233324, "lat": 39.91411590576172, "lon": -104.97241973876953, "trip": "114902097", "route_id": "120", "stop_id": "24225", "vehicle_id": "1A5C9CB6923C9B34E063DD4D1FACBFC2", "vehicle_label": "6211"}, {"vehicle_update_ts": 1718233317, "lat": 39.656715393066406, "lon": -104.99793243408203, "trip": "114910488", "route_id": "51", "stop_id": "20171", "vehicle_id": "1A5C9CB6923E9B34E063DD4D1FACBFC2", "vehicle_label": "6213"}, {"vehicle_update_ts": 1718233315, "lat": 39.740631103515625, "lon": -104.94080352783203, "trip": "114908795", "route_id": "40", "stop_id": "13093", "vehicle_id": "1A5C9CB692409B34E063DD4D1FACBFC2", "vehicle_label": "6215"}, {"vehicle_update_ts": 1718233314, "lat": 40.05744934082031, "lon": -105.28215026855469, "trip": "114922511", "route_id": "SKIP", "stop_id": "12554", "vehicle_id": "1A5C9CB692419B34E063DD4D1FACBFC2", "vehicle_label": "6216"}, {"vehicle_update_ts": 1718233322, "lat": 40.046234130859375, "lon": -105.28205108642578, "trip": "114922476", "route_id": "SKIP", "stop_id": "12581", "vehicle_id": "1A5C9CB692499B34E063DD4D1FACBFC2", "vehicle_label": "6224"}, {"vehicle_update_ts": 1718233326, "lat": 40.006649017333984, "lon": -105.2734146118164, "trip": "114922477", "route_id": "SKIP", "stop_id": "12432", "vehicle_id": "1A5C9CB6924B9B34E063DD4D1FACBFC2", "vehicle_label": "6226"}, {"vehicle_update_ts": 1718233318, "lat": 39.76111602783203, "lon": -104.95706939697266, "trip": "114909446", "route_id": "43", "stop_id": "15231", "vehicle_id": "1A5C9CB6924E9B34E063DD4D1FACBFC2", "vehicle_label": "6229"}, {"vehicle_update_ts": 1718233309, "lat": 39.765167236328125, "lon": -104.90353393554688, "trip": "114909522", "route_id": "43", "stop_id": "15249", "vehicle_id": "1A5C9CB6924F9B34E063DD4D1FACBFC2", "vehicle_label": "6230"}, {"vehicle_update_ts": 1718233315, "lat": 39.740699768066406, "lon": -104.98870086669922, "trip": "114910183", "route_id": "48", "stop_id": "17698", "vehicle_id": "1A5C9CB692529B34E063DD4D1FACBFC2", "vehicle_label": "6233"}, {"vehicle_update_ts": 1718233311, "lat": 40.00960159301758, "lon": -105.27639770507812, "trip": "114922552", "route_id": "SKIP", "stop_id": "12574", "vehicle_id": "1A5C9CB692599B34E063DD4D1FACBFC2", "vehicle_label": "6240"}, {"vehicle_update_ts": 1718233311, "lat": 39.69990158081055, "lon": -104.98757934570312, "trip": "114900824", "route_id": "11", "stop_id": "12526", "vehicle_id": "1A5C9CB6925C9B34E063DD4D1FACBFC2", "vehicle_label": "6243"}, {"vehicle_update_ts": 1718233297, "lat": 39.69673156738281, "lon": -105.06816864013672, "trip": "114900823", "route_id": "11", "stop_id": "15425", "vehicle_id": "1A5C9CB6925E9B34E063DD4D1FACBFC2", "vehicle_label": "6245"}, {"vehicle_update_ts": 1718233324, "lat": 39.70753479003906, "lon": -104.97341918945312, "trip": "114901975", "route_id": "12", "stop_id": "13428", "vehicle_id": "1A5C9CB692639B34E063DD4D1FACBFC2", "vehicle_label": "6250"}, {"vehicle_update_ts": 1718233305, "lat": 39.74038314819336, "lon": -105.01789855957031, "trip": "114904920", "route_id": "16", "stop_id": "18863", "vehicle_id": "1A5C9CB692649B34E063DD4D1FACBFC2", "vehicle_label": "6251"}, {"vehicle_update_ts": 1718233322, "lat": 39.97195053100586, "lon": -105.25223541259766, "trip": "114906012", "route_id": "206", "stop_id": "14089", "vehicle_id": "1A5C9CB692659B34E063DD4D1FACBFC2", "vehicle_label": "6252"}, {"vehicle_update_ts": 1718233306, "lat": 40.00016784667969, "lon": -105.15858459472656, "trip": "114919153", "route_id": "225", "stop_id": "22830", "vehicle_id": "1A5C9CB692699B34E063DD4D1FACBFC2", "vehicle_label": "6256"}, {"vehicle_update_ts": 1718233322, "lat": 39.966583251953125, "lon": -105.256103515625, "trip": "114922478", "route_id": "SKIP", "stop_id": "19725", "vehicle_id": "1A5C9CB6926B9B34E063DD4D1FACBFC2", "vehicle_label": "6258"}, {"vehicle_update_ts": 1718233315, "lat": 39.667518615722656, "lon": -104.84288024902344, "trip": "114902805", "route_id": "130", "stop_id": "17356", "vehicle_id": "1A5C9CB692709B34E063DD4D1FACBFC2", "vehicle_label": "6263"}, {"vehicle_update_ts": 1718233326, "lat": 39.6529655456543, "lon": -104.79528045654297, "trip": "114903033", "route_id": "133", "stop_id": "26393", "vehicle_id": "1A5C9CB692729B34E063DD4D1FACBFC2", "vehicle_label": "6265"}, {"vehicle_update_ts": 1718233311, "lat": 39.75446701049805, "lon": -105.00178527832031, "trip": "114903831", "route_id": "15", "stop_id": "34327", "vehicle_id": "1A5C9CB692749B34E063DD4D1FACBFC2", "vehicle_label": "6267"}, {"vehicle_update_ts": 1718233298, "lat": 39.64061737060547, "lon": -104.82894897460938, "trip": "114903253", "route_id": "139", "stop_id": "16195", "vehicle_id": "1A5C9CB692769B34E063DD4D1FACBFC2", "vehicle_label": "6269"}, {"vehicle_update_ts": 1718233285, "lat": 39.686100006103516, "lon": -104.84715270996094, "trip": "114902547", "route_id": "121", "stop_id": "15931", "vehicle_id": "1A5C9CB692799B34E063DD4D1FACBFC2", "vehicle_label": "6272"}, {"vehicle_update_ts": 1718233317, "lat": 39.7814826965332, "lon": -104.88265228271484, "trip": "114909092", "route_id": "42", "stop_id": "33060", "vehicle_id": "1A5C9CB6927B9B34E063DD4D1FACBFC2", "vehicle_label": "6274"}, {"vehicle_update_ts": 1718233317, "lat": 39.753334045410156, "lon": -105.00088500976562, "trip": "114903866", "route_id": "15", "stop_id": "34331", "vehicle_id": "1A5C9CB6927C9B34E063DD4D1FACBFC2", "vehicle_label": "6275"}, {"vehicle_update_ts": 1718233316, "lat": 39.773231506347656, "lon": -104.80979919433594, "trip": "114902562", "route_id": "121", "stop_id": "25479", "vehicle_id": "1A5C9CB6927D9B34E063DD4D1FACBFC2", "vehicle_label": "6276"}, {"vehicle_update_ts": 1718233324, "lat": 39.75226593017578, "lon": -104.99653625488281, "trip": "114903886", "route_id": "15", "stop_id": "17834", "vehicle_id": "1A5C9CB6927E9B34E063DD4D1FACBFC2", "vehicle_label": "6277"}, {"vehicle_update_ts": 1718233300, "lat": 39.740234375, "lon": -104.87108612060547, "trip": "114903885", "route_id": "15", "stop_id": "12868", "vehicle_id": "1A5C9CB6927F9B34E063DD4D1FACBFC2", "vehicle_label": "6278"}, {"vehicle_update_ts": 1718233315, "lat": 39.778934478759766, "lon": -104.8201675415039, "trip": "114909117", "route_id": "42", "stop_id": "20644", "vehicle_id": "1A5C9CB692809B34E063DD4D1FACBFC2", "vehicle_label": "6279"}, {"vehicle_update_ts": 1718233316, "lat": 39.735050201416016, "lon": -104.84721374511719, "trip": "114902618", "route_id": "121", "stop_id": "33228", "vehicle_id": "1A5C9CB692819B34E063DD4D1FACBFC2", "vehicle_label": "6280"}, {"vehicle_update_ts": 1718233297, "lat": 39.70869827270508, "lon": -104.8108139038086, "trip": "114903032", "route_id": "133", "stop_id": "26651", "vehicle_id": "1A5C9CB692829B34E063DD4D1FACBFC2", "vehicle_label": "6281"}, {"vehicle_update_ts": 1718233255, "lat": 39.70854949951172, "lon": -104.81863403320312, "trip": "114902812", "route_id": "130", "stop_id": "26332", "vehicle_id": "1A5C9CB692869B34E063DD4D1FACBFC2", "vehicle_label": "6285"}, {"vehicle_update_ts": 1718233316, "lat": 39.75508117675781, "lon": -105.00029754638672, "trip": "114896643", "route_id": "10", "stop_id": "34328", "vehicle_id": "1A5C9CB692889B34E063DD4D1FACBFC2", "vehicle_label": "6286"}, {"vehicle_update_ts": 1718233313, "lat": 39.749881744384766, "lon": -104.77243041992188, "trip": "114905156", "route_id": "169", "stop_id": "24519", "vehicle_id": "1A5C9CB692899B34E063DD4D1FACBFC2", "vehicle_label": "6287"}, {"vehicle_update_ts": 1718233326, "lat": 39.74024963378906, "lon": -104.91667938232422, "trip": "114903932", "route_id": "15", "stop_id": "12907", "vehicle_id": "1A5C9CB6928B9B34E063DD4D1FACBFC2", "vehicle_label": "6290"}, {"vehicle_update_ts": 1718233305, "lat": 39.65318298339844, "lon": -104.76380157470703, "trip": "114903075", "route_id": "133", "stop_id": "26125", "vehicle_id": "1A5C9CB6928C9B34E063DD4D1FACBFC2", "vehicle_label": "6291"}, {"vehicle_update_ts": 1718233323, "lat": 39.77293395996094, "lon": -104.80149841308594, "trip": "114909150", "route_id": "42", "stop_id": "25480", "vehicle_id": "1A5C9CB6928D9B34E063DD4D1FACBFC2", "vehicle_label": "6292"}, {"vehicle_update_ts": 1718233302, "lat": 39.732948303222656, "lon": -104.86589813232422, "trip": "114899864", "route_id": "105", "stop_id": "14251", "vehicle_id": "1A5C9CB6928E9B34E063DD4D1FACBFC2", "vehicle_label": "6293"}, {"vehicle_update_ts": 1718233318, "lat": 39.78711700439453, "lon": -104.94989776611328, "trip": "114910226", "route_id": "48", "stop_id": "16653", "vehicle_id": "1A5C9CB6928F9B34E063DD4D1FACBFC2", "vehicle_label": "6294"}, {"vehicle_update_ts": 1718233318, "lat": 39.73796844482422, "lon": -105.02581787109375, "trip": "114896397", "route_id": "1", "stop_id": "21279", "vehicle_id": "1A5C9CB692919B34E063DD4D1FACBFC2", "vehicle_label": "6296"}, {"vehicle_update_ts": 1718233317, "lat": 39.69878387451172, "lon": -104.91913604736328, "trip": "114900825", "route_id": "11", "stop_id": "19855", "vehicle_id": "1A5C9CB692939B34E063DD4D1FACBFC2", "vehicle_label": "6298"}, {"vehicle_update_ts": 1718233305, "lat": 39.726600646972656, "lon": -104.84715270996094, "trip": "114902583", "route_id": "121", "stop_id": "15926", "vehicle_id": "1A5C9CB692959B34E063DD4D1FACBFC2", "vehicle_label": "6301"}, {"vehicle_update_ts": 1718233312, "lat": 39.67509841918945, "lon": -104.86581420898438, "trip": "114899824", "route_id": "105", "stop_id": "14269", "vehicle_id": "1A5C9CB6929B9B34E063DD4D1FACBFC2", "vehicle_label": "6307"}, {"vehicle_update_ts": 1718232837, "lat": 39.73696517944336, "lon": -104.82344818115234, "trip": "", "route_id": "", "stop_id": "", "vehicle_id": "1A5C9CB6929E9B34E063DD4D1FACBFC2", "vehicle_label": "6310"}, {"vehicle_update_ts": 1718233304, "lat": 39.66758346557617, "lon": -104.79644775390625, "trip": "114902847", "route_id": "130", "stop_id": "18954", "vehicle_id": "1A5C9CB6929F9B34E063DD4D1FACBFC2", "vehicle_label": "6311"}, {"vehicle_update_ts": 1718233320, "lat": 39.696468353271484, "lon": -104.86730194091797, "trip": "114900783", "route_id": "11", "stop_id": "15369", "vehicle_id": "1A5C9CB692A19B34E063DD4D1FACBFC2", "vehicle_label": "6313"}, {"vehicle_update_ts": 1718233322, "lat": 39.740081787109375, "lon": -104.94960021972656, "trip": "114903832", "route_id": "15", "stop_id": "12840", "vehicle_id": "1A5C9CB692A29B34E063DD4D1FACBFC2", "vehicle_label": "6314"}, {"vehicle_update_ts": 1718233320, "lat": 39.733150482177734, "lon": -105.05091857910156, "trip": "114912503", "route_id": "9", "stop_id": "10075", "vehicle_id": "1A5C9CB692A39B34E063DD4D1FACBFC2", "vehicle_label": "6315"}, {"vehicle_update_ts": 1718233318, "lat": 39.78105163574219, "lon": -105.08135223388672, "trip": "114907652", "route_id": "32", "stop_id": "34537", "vehicle_id": "1A5C9CB692A79B34E063DD4D1FACBFC2", "vehicle_label": "6319"}, {"vehicle_update_ts": 1718233319, "lat": 39.74778366088867, "lon": -104.99317932128906, "trip": "114909447", "route_id": "43", "stop_id": "17761", "vehicle_id": "1A5C9CB692A89B34E063DD4D1FACBFC2", "vehicle_label": "6320"}, {"vehicle_update_ts": 1718233326, "lat": 39.6929817199707, "lon": -104.97848510742188, "trip": "114901926", "route_id": "12", "stop_id": "15056", "vehicle_id": "1A5C9CB692A99B34E063DD4D1FACBFC2", "vehicle_label": "6321"}, {"vehicle_update_ts": 1718233322, "lat": 39.750518798828125, "lon": -104.98750305175781, "trip": "", "route_id": "", "stop_id": "", "vehicle_id": "1A5C9CB692AA9B34E063DD4D1FACBFC2", "vehicle_label": "6322"}, {"vehicle_update_ts": 1718233320, "lat": 39.751033782958984, "lon": -104.9218521118164, "trip": "114905651", "route_id": "20", "stop_id": "10592", "vehicle_id": "1A5C9CB692AD9B34E063DD4D1FACBFC2", "vehicle_label": "6325"}, {"vehicle_update_ts": 1718233326, "lat": 39.69241714477539, "lon": -104.831298828125, "trip": "114900835", "route_id": "11", "stop_id": "24462", "vehicle_id": "1A5C9CB692AE9B34E063DD4D1FACBFC2", "vehicle_label": "6326"}, {"vehicle_update_ts": 1718233236, "lat": 39.70823287963867, "lon": -104.81878662109375, "trip": "114900796", "route_id": "11", "stop_id": "26338", "vehicle_id": "1A5C9CB692B09B34E063DD4D1FACBFC2", "vehicle_label": "6328"}, {"vehicle_update_ts": 1718233324, "lat": 39.737998962402344, "lon": -105.01599884033203, "trip": "", "route_id": "", "stop_id": "", "vehicle_id": "1A5C9CB692B39B34E063DD4D1FACBFC2", "vehicle_label": "6331"}, {"vehicle_update_ts": 1718233326, "lat": 39.74716567993164, "lon": -104.98968505859375, "trip": "114908381", "route_id": "38", "stop_id": "17733", "vehicle_id": "1A5C9CB692B89B34E063DD4D1FACBFC2", "vehicle_label": "6336"}, {"vehicle_update_ts": 1718233326, "lat": 39.75071716308594, "lon": -105.21378326416016, "trip": "114905397", "route_id": "17", "stop_id": "10373", "vehicle_id": "1A5C9CB692B99B34E063DD4D1FACBFC2", "vehicle_label": "6337"}, {"vehicle_update_ts": 1718233298, "lat": 39.84718322753906, "lon": -104.97783660888672, "trip": "114911375", "route_id": "7", "stop_id": "17200", "vehicle_id": "1A5C9CB692BF9B34E063DD4D1FACBFC2", "vehicle_label": "6343"}, {"vehicle_update_ts": 1718233326, "lat": 39.729881286621094, "lon": -104.91242980957031, "trip": "114911144", "route_id": "65", "stop_id": "15495", "vehicle_id": "1A5C9CB692C39B34E063DD4D1FACBFC2", "vehicle_label": "6347"}, {"vehicle_update_ts": 1718233305, "lat": 39.696983337402344, "lon": -104.9405517578125, "trip": "114908725", "route_id": "40", "stop_id": "13128", "vehicle_id": "1A5C9CB692C49B34E063DD4D1FACBFC2", "vehicle_label": "6348"}, {"vehicle_update_ts": 1718233304, "lat": 39.86356735229492, "lon": -105.04096984863281, "trip": "114912641", "route_id": "92", "stop_id": "18332", "vehicle_id": "1A5C9CB692C79B34E063DD4D1FACBFC2", "vehicle_label": "6351"}, {"vehicle_update_ts": 1718233311, "lat": 39.95009994506836, "lon": -104.78565216064453, "trip": "114910746", "route_id": "520", "stop_id": "34389", "vehicle_id": "1A5C9CB692C99B34E063DD4D1FACBFC2", "vehicle_label": "6353"}, {"vehicle_update_ts": 1718233322, "lat": 39.73255157470703, "lon": -105.16416931152344, "trip": "114905396", "route_id": "17", "stop_id": "24161", "vehicle_id": "1A5C9CB692CD9B34E063DD4D1FACBFC2", "vehicle_label": "6357"}, {"vehicle_update_ts": 1718233286, "lat": 39.743099212646484, "lon": -104.97339630126953, "trip": "114901927", "route_id": "12", "stop_id": "13424", "vehicle_id": "1A5C9CB692D09B34E063DD4D1FACBFC2", "vehicle_label": "6360"}, {"vehicle_update_ts": 1718233308, "lat": 39.747318267822266, "lon": -104.97760009765625, "trip": "114906750", "route_id": "28", "stop_id": "35104", "vehicle_id": "1A5C9CB692D39B34E063DD4D1FACBFC2", "vehicle_label": "6363"}, {"vehicle_update_ts": 1718233309, "lat": 39.656517028808594, "lon": -104.99943542480469, "trip": "114901976", "route_id": "12", "stop_id": "26176", "vehicle_id": "1A5C9CB692D49B34E063DD4D1FACBFC2", "vehicle_label": "6364"}, {"vehicle_update_ts": 1718233304, "lat": 39.739498138427734, "lon": -104.98726654052734, "trip": "114904983", "route_id": "16", "stop_id": "12850", "vehicle_id": "1A5C9CB692D59B34E063DD4D1FACBFC2", "vehicle_label": "6365"}, {"vehicle_update_ts": 1718233280, "lat": 39.73753356933594, "lon": -105.12024688720703, "trip": "114904987", "route_id": "16", "stop_id": "33963", "vehicle_id": "1A5C9CB692D69B34E063DD4D1FACBFC2", "vehicle_label": "6366"}, {"vehicle_update_ts": 1718233322, "lat": 39.71103286743164, "lon": -105.0245132446289, "trip": "114908444", "route_id": "4", "stop_id": "11991", "vehicle_id": "1A5C9CB692D79B34E063DD4D1FACBFC2", "vehicle_label": "6367"}, {"vehicle_update_ts": 1718233305, "lat": 39.76511764526367, "lon": -104.90350341796875, "trip": "114911638", "route_id": "73", "stop_id": "19285", "vehicle_id": "1A5C9CB692DB9B34E063DD4D1FACBFC2", "vehicle_label": "6370"}, {"vehicle_update_ts": 1718233303, "lat": 39.6746826171875, "lon": -104.8743667602539, "trip": "114906243", "route_id": "21", "stop_id": "14541", "vehicle_id": "1A5C9CB692DC9B34E063DD4D1FACBFC2", "vehicle_label": "6372"}, {"vehicle_update_ts": 1718233319, "lat": 39.5744514465332, "lon": -104.79067993164062, "trip": "114910245", "route_id": "483", "stop_id": "22256", "vehicle_id": "1A5C9CB692DD9B34E063DD4D1FACBFC2", "vehicle_label": "6373"}, {"vehicle_update_ts": 1718233318, "lat": 39.65266799926758, "lon": -105.08123016357422, "trip": "114907124", "route_id": "30", "stop_id": "17056", "vehicle_id": "1A5C9CB692DE9B34E063DD4D1FACBFC2", "vehicle_label": "6374"}, {"vehicle_update_ts": 1718233316, "lat": 39.61439895629883, "lon": -105.09103393554688, "trip": "114912726", "route_id": "99", "stop_id": "16983", "vehicle_id": "1A5C9CB692DF9B34E063DD4D1FACBFC2", "vehicle_label": "6375"}, {"vehicle_update_ts": 1718233314, "lat": 39.67940139770508, "lon": -104.93675231933594, "trip": "114906275", "route_id": "21", "stop_id": "26152", "vehicle_id": "1A5C9CB692E09B34E063DD4D1FACBFC2", "vehicle_label": "6376"}, {"vehicle_update_ts": 1718233316, "lat": 39.90911865234375, "lon": -105.0961685180664, "trip": "114911840", "route_id": "76", "stop_id": "18554", "vehicle_id": "1A5C9CB692E49B34E063DD4D1FACBFC2", "vehicle_label": "6380"}, {"vehicle_update_ts": 1718233302, "lat": 39.73776626586914, "lon": -105.02501678466797, "trip": "114907422", "route_id": "31", "stop_id": "13703", "vehicle_id": "1A5C9CB692E69B34E063DD4D1FACBFC2", "vehicle_label": "6382"}, {"vehicle_update_ts": 1718233322, "lat": 39.769317626953125, "lon": -105.02518463134766, "trip": "114907445", "route_id": "31", "stop_id": "13718", "vehicle_id": "1A5C9CB692EA9B34E063DD4D1FACBFC2", "vehicle_label": "6386"}, {"vehicle_update_ts": 1718233319, "lat": 39.66716766357422, "lon": -105.0418701171875, "trip": "114908051", "route_id": "35", "stop_id": "16243", "vehicle_id": "1A5C9CB692EB9B34E063DD4D1FACBFC2", "vehicle_label": "6387"}, {"vehicle_update_ts": 1718233313, "lat": 39.691917419433594, "lon": -104.90363311767578, "trip": "114911637", "route_id": "73", "stop_id": "19487", "vehicle_id": "1A5C9CB692EC9B34E063DD4D1FACBFC2", "vehicle_label": "6388"}, {"vehicle_update_ts": 1718233326, "lat": 39.68841552734375, "lon": -105.10034942626953, "trip": "114912758", "route_id": "99", "stop_id": "14051", "vehicle_id": "1A5C9CB692ED9B34E063DD4D1FACBFC2", "vehicle_label": "6389"}, {"vehicle_update_ts": 1718233190, "lat": 39.68170166015625, "lon": -105.12328338623047, "trip": "114906265", "route_id": "21", "stop_id": "17522", "vehicle_id": "1A5C9CB692F09B34E063DD4D1FACBFC2", "vehicle_label": "6392"}, {"vehicle_update_ts": 1718233307, "lat": 39.74005126953125, "lon": -104.86616516113281, "trip": "114903833", "route_id": "15", "stop_id": "12908", "vehicle_id": "1A5C9CB692F29B34E063DD4D1FACBFC2", "vehicle_label": "6394"}, {"vehicle_update_ts": 1718233307, "lat": 39.76374816894531, "lon": -104.77471923828125, "trip": "114909849", "route_id": "45", "stop_id": "25805", "vehicle_id": "1A5C9CB692F39B34E063DD4D1FACBFC2", "vehicle_label": "6395"}, {"vehicle_update_ts": 1718233315, "lat": 39.69260025024414, "lon": -104.86605072021484, "trip": "114899866", "route_id": "105", "stop_id": "14231", "vehicle_id": "1A5C9CB692F59B34E063DD4D1FACBFC2", "vehicle_label": "6397"}, {"vehicle_update_ts": 1718233319, "lat": 39.68503189086914, "lon": -104.9643325805664, "trip": "114906625", "route_id": "24", "stop_id": "26299", "vehicle_id": "1A5C9CB692F79B34E063DD4D1FACBFC2", "vehicle_label": "6399"}, {"vehicle_update_ts": 1718233326, "lat": 39.805633544921875, "lon": -104.91314697265625, "trip": "114912340", "route_id": "88", "stop_id": "34793", "vehicle_id": "1A5C9CB692FB9B34E063DD4D1FACBFC2", "vehicle_label": "6403"}, {"vehicle_update_ts": 1718233322, "lat": 39.70724868774414, "lon": -105.08443450927734, "trip": "114907073", "route_id": "3", "stop_id": "24858", "vehicle_id": "1A5C9CB692FC9B34E063DD4D1FACBFC2", "vehicle_label": "6404"}, {"vehicle_update_ts": 1718233314, "lat": 39.80553436279297, "lon": -104.92603302001953, "trip": "114910336", "route_id": "49", "stop_id": "11492", "vehicle_id": "1A5C9CB692FE9B34E063DD4D1FACBFC2", "vehicle_label": "6406"}, {"vehicle_update_ts": 1718233313, "lat": 39.777950286865234, "lon": -105.00170135498047, "trip": "114910693", "route_id": "52", "stop_id": "11224", "vehicle_id": "1A5C9CB693039B34E063DD4D1FACBFC2", "vehicle_label": "6411"}, {"vehicle_update_ts": 1718233308, "lat": 39.695648193359375, "lon": -105.0250015258789, "trip": "114903367", "route_id": "14", "stop_id": "15355", "vehicle_id": "1A5C9CB693049B34E063DD4D1FACBFC2", "vehicle_label": "6412"}, {"vehicle_update_ts": 1718233322, "lat": 39.773868560791016, "lon": -105.00181579589844, "trip": "114910655", "route_id": "52", "stop_id": "14993", "vehicle_id": "1A5C9CB693059B34E063DD4D1FACBFC2", "vehicle_label": "6413"}, {"vehicle_update_ts": 1718233311, "lat": 39.785465240478516, "lon": -104.89344787597656, "trip": "114912347", "route_id": "88", "stop_id": "33025", "vehicle_id": "1A5C9CB693079B34E063DD4D1FACBFC2", "vehicle_label": "6415"}, {"vehicle_update_ts": 1718233305, "lat": 39.75870132446289, "lon": -105.02532958984375, "trip": "114907567", "route_id": "31", "stop_id": "13714", "vehicle_id": "1A5C9CB693099B34E063DD4D1FACBFC2", "vehicle_label": "6502"}, {"vehicle_update_ts": 1718233314, "lat": 39.71198272705078, "lon": -105.02523040771484, "trip": "114907501", "route_id": "31", "stop_id": "13782", "vehicle_id": "1A5C9CB6930C9B34E063DD4D1FACBFC2", "vehicle_label": "6505"}, {"vehicle_update_ts": 1718233320, "lat": 39.808048248291016, "lon": -105.025146484375, "trip": "114907387", "route_id": "31", "stop_id": "13743", "vehicle_id": "1A5C9CB6930D9B34E063DD4D1FACBFC2", "vehicle_label": "6506"}, {"vehicle_update_ts": 1718233306, "lat": 39.63404846191406, "lon": -105.02528381347656, "trip": "114906833", "route_id": "29", "stop_id": "13843", "vehicle_id": "1A5C9CB6930F9B34E063DD4D1FACBFC2", "vehicle_label": "6508"}, {"vehicle_update_ts": 1718233303, "lat": 39.803466796875, "lon": -105.0251693725586, "trip": "114907457", "route_id": "31", "stop_id": "34532", "vehicle_id": "1A5C9CB693109B34E063DD4D1FACBFC2", "vehicle_label": "6509"}, {"vehicle_update_ts": 1718233311, "lat": 39.739784240722656, "lon": -104.90343475341797, "trip": "114911617", "route_id": "73", "stop_id": "25272", "vehicle_id": "1A5C9CB693119B34E063DD4D1FACBFC2", "vehicle_label": "6510"}, {"vehicle_update_ts": 1718233303, "lat": 39.71125030517578, "lon": -105.02082061767578, "trip": "114908459", "route_id": "4", "stop_id": "11992", "vehicle_id": "1A5C9CB693129B34E063DD4D1FACBFC2", "vehicle_label": "6511"}, {"vehicle_update_ts": 1718233320, "lat": 39.68283462524414, "lon": -105.02493286132812, "trip": "114907398", "route_id": "31", "stop_id": "13800", "vehicle_id": "1A5C9CB693149B34E063DD4D1FACBFC2", "vehicle_label": "6513"}, {"vehicle_update_ts": 1718233201, "lat": 39.67753219604492, "lon": -105.02525329589844, "trip": "114908134", "route_id": "36", "stop_id": "26186", "vehicle_id": "1A5C9CB693159B34E063DD4D1FACBFC2", "vehicle_label": "6514"}, {"vehicle_update_ts": 1718233301, "lat": 39.67573165893555, "lon": -105.0251693725586, "trip": "114908020", "route_id": "35", "stop_id": "13823", "vehicle_id": "1A5C9CB693179B34E063DD4D1FACBFC2", "vehicle_label": "6516"}, {"vehicle_update_ts": 1718233319, "lat": 39.68470001220703, "lon": -104.81936645507812, "trip": "114906295", "route_id": "21", "stop_id": "16384", "vehicle_id": "1A5C9CB693199B34E063DD4D1FACBFC2", "vehicle_label": "6518"}, {"vehicle_update_ts": 1718233317, "lat": 39.80906677246094, "lon": -105.02543640136719, "trip": "114907536", "route_id": "31", "stop_id": "34531", "vehicle_id": "1A5C9CB6931A9B34E063DD4D1FACBFC2", "vehicle_label": "6519"}, {"vehicle_update_ts": 1718233322, "lat": 39.68033218383789, "lon": -104.99165344238281, "trip": "114906286", "route_id": "21", "stop_id": "13622", "vehicle_id": "1A5C9CB6931B9B34E063DD4D1FACBFC2", "vehicle_label": "6520"}, {"vehicle_update_ts": 1718233319, "lat": 39.76996612548828, "lon": -105.01118469238281, "trip": "114909663", "route_id": "44", "stop_id": "16716", "vehicle_id": "1A5C9CB693219B34E063DD4D1FACBFC2", "vehicle_label": "6526"}, {"vehicle_update_ts": 1718233297, "lat": 39.85689926147461, "lon": -105.05374908447266, "trip": "114912618", "route_id": "92", "stop_id": "21013", "vehicle_id": "1A5C9CB693239B34E063DD4D1FACBFC2", "vehicle_label": "6528"}, {"vehicle_update_ts": 1718233322, "lat": 39.7635498046875, "lon": -104.90350341796875, "trip": "114911179", "route_id": "65", "stop_id": "15249", "vehicle_id": "1A5C9CB693279B34E063DD4D1FACBFC2", "vehicle_label": "6532"}, {"vehicle_update_ts": 1718233313, "lat": 39.77914810180664, "lon": -105.06271362304688, "trip": "114910533", "route_id": "51", "stop_id": "11141", "vehicle_id": "1A5C9CB6932A9B34E063DD4D1FACBFC2", "vehicle_label": "6535"}, {"vehicle_update_ts": 1718233309, "lat": 39.62248229980469, "lon": -104.95978546142578, "trip": "", "route_id": "", "stop_id": "", "vehicle_id": "1A5C9CB6932C9B34E063DD4D1FACBFC2", "vehicle_label": "6539"}, {"vehicle_update_ts": 1718233296, "lat": 39.75033187866211, "lon": -104.99597930908203, "trip": "114908337", "route_id": "38", "stop_id": "17750", "vehicle_id": "1A5C9CB6932E9B34E063DD4D1FACBFC2", "vehicle_label": "6541"}, {"vehicle_update_ts": 1718233221, "lat": 39.826148986816406, "lon": -104.94273376464844, "trip": "114911458", "route_id": "72", "stop_id": "24438", "vehicle_id": "1A5C9CB6932F9B34E063DD4D1FACBFC2", "vehicle_label": "6542"}, {"vehicle_update_ts": 1718233298, "lat": 39.79159927368164, "lon": -105.11039733886719, "trip": "114896722", "route_id": "100", "stop_id": "34524", "vehicle_id": "1A5C9CB693329B34E063DD4D1FACBFC2", "vehicle_label": "6545"}, {"vehicle_update_ts": 1718233315, "lat": 39.79264831542969, "lon": -104.82318115234375, "trip": "114902584", "route_id": "121", "stop_id": "15276", "vehicle_id": "1A5C9CB693349B34E063DD4D1FACBFC2", "vehicle_label": "6547"}, {"vehicle_update_ts": 1718233322, "lat": 39.76694869995117, "lon": -104.8904037475586, "trip": "114899841", "route_id": "105", "stop_id": "34488", "vehicle_id": "1A5C9CB693359B34E063DD4D1FACBFC2", "vehicle_label": "6548"}, {"vehicle_update_ts": 1718233311, "lat": 39.73970031738281, "lon": -105.05332946777344, "trip": "114910532", "route_id": "51", "stop_id": "33968", "vehicle_id": "1A5C9CB693379B34E063DD4D1FACBFC2", "vehicle_label": "6537"}, {"vehicle_update_ts": 1718233320, "lat": 39.7727165222168, "lon": -104.78778076171875, "trip": "114908161", "route_id": "37", "stop_id": "26163", "vehicle_id": "1A5C9CB6933A9B34E063DD4D1FACBFC2", "vehicle_label": "6551"}, {"vehicle_update_ts": 1718233311, "lat": 39.72556686401367, "lon": -104.94824981689453, "trip": "114910968", "route_id": "6", "stop_id": "11576", "vehicle_id": "1A5C9CB6933E9B34E063DD4D1FACBFC2", "vehicle_label": "6555"}, {"vehicle_update_ts": 1718233326, "lat": 39.67599868774414, "lon": -105.05316925048828, "trip": "114910487", "route_id": "51", "stop_id": "16580", "vehicle_id": "1A5C9CB693429B34E063DD4D1FACBFC2", "vehicle_label": "6559"}, {"vehicle_update_ts": 1718233316, "lat": 39.86053466796875, "lon": -105.05438232421875, "trip": "", "route_id": "", "stop_id": "", "vehicle_id": "1A5C9CB693479B34E063DD4D1FACBFC2", "vehicle_label": "6564"}, {"vehicle_update_ts": 1718233309, "lat": 39.7730827331543, "lon": -104.9429702758789, "trip": "114908791", "route_id": "40", "stop_id": "14632", "vehicle_id": "1A5C9CB6934A9B34E063DD4D1FACBFC2", "vehicle_label": "6567"}, {"vehicle_update_ts": 1718233298, "lat": 39.907501220703125, "lon": -105.09093475341797, "trip": "114902106", "route_id": "120", "stop_id": "33527", "vehicle_id": "1A5C9CB6934D9B34E063DD4D1FACBFC2", "vehicle_label": "6570"}, {"vehicle_update_ts": 1718233312, "lat": 39.74018478393555, "lon": -104.97480010986328, "trip": "114901999", "route_id": "12", "stop_id": "13187", "vehicle_id": "1A5C9CB6934E9B34E063DD4D1FACBFC2", "vehicle_label": "6571"}, {"vehicle_update_ts": 1718233324, "lat": 39.67878341674805, "lon": -104.93675231933594, "trip": "114908800", "route_id": "40", "stop_id": "13111", "vehicle_id": "1A5C9CB693539B34E063DD4D1FACBFC2", "vehicle_label": "6576"}, {"vehicle_update_ts": 1718233302, "lat": 39.679317474365234, "lon": -104.93678283691406, "trip": "114908705", "route_id": "40", "stop_id": "34724", "vehicle_id": "1A5C9CB693549B34E063DD4D1FACBFC2", "vehicle_label": "6577"}, {"vehicle_update_ts": 1718233308, "lat": 39.681331634521484, "lon": -104.91301727294922, "trip": "114911178", "route_id": "65", "stop_id": "15533", "vehicle_id": "1A5C9CB693569B34E063DD4D1FACBFC2", "vehicle_label": "6579"}, {"vehicle_update_ts": 1718233326, "lat": 39.8717155456543, "lon": -104.99673461914062, "trip": "114911942", "route_id": "8", "stop_id": "23993", "vehicle_id": "1A5C9CB693579B34E063DD4D1FACBFC2", "vehicle_label": "6580"}, {"vehicle_update_ts": 1718233306, "lat": 39.536399841308594, "lon": -104.85124969482422, "trip": "114910257", "route_id": "483", "stop_id": "26437", "vehicle_id": "1A5C9CB693599B34E063DD4D1FACBFC2", "vehicle_label": "6582"}, {"vehicle_update_ts": 1718233322, "lat": 39.64078140258789, "lon": -104.88491821289062, "trip": "114911599", "route_id": "73", "stop_id": "17448", "vehicle_id": "1A5C9CB6935B9B34E063DD4D1FACBFC2", "vehicle_label": "6584"}, {"vehicle_update_ts": 1718233318, "lat": 39.61375045776367, "lon": -105.09221649169922, "trip": "114910824", "route_id": "59", "stop_id": "16983", "vehicle_id": "1A5C9CB6935C9B34E063DD4D1FACBFC2", "vehicle_label": "6585"}, {"vehicle_update_ts": 1718233312, "lat": 39.804481506347656, "lon": -105.02490234375, "trip": "114907548", "route_id": "31", "stop_id": "13738", "vehicle_id": "1A5C9CB693619B34E063DD4D1FACBFC2", "vehicle_label": "6590"}, {"vehicle_update_ts": 1718233314, "lat": 39.59503173828125, "lon": -104.9489517211914, "trip": "114911253", "route_id": "66", "stop_id": "12254", "vehicle_id": "1A5C9CB693629B34E063DD4D1FACBFC2", "vehicle_label": "6591"}, {"vehicle_update_ts": 1718233305, "lat": 39.99788284301758, "lon": -105.26026916503906, "trip": "114914067", "route_id": "BOND", "stop_id": "12438", "vehicle_id": "1A5C9CB693669B34E063DD4D1FACBFC2", "vehicle_label": "6595"}, {"vehicle_update_ts": 1718233299, "lat": 40.01481628417969, "lon": -105.24036407470703, "trip": "114918961", "route_id": "JUMP", "stop_id": "19186", "vehicle_id": "1A5C9CB693679B34E063DD4D1FACBFC2", "vehicle_label": "6596"}, {"vehicle_update_ts": 1718233322, "lat": 40.000099182128906, "lon": -105.22209930419922, "trip": "114919185", "route_id": "225", "stop_id": "22812", "vehicle_id": "1A5C9CB693699B34E063DD4D1FACBFC2", "vehicle_label": "6598"}, {"vehicle_update_ts": 1718233323, "lat": 40.02931594848633, "lon": -105.2352523803711, "trip": "114906085", "route_id": "208", "stop_id": "16930", "vehicle_id": "1A5C9CB693709B34E063DD4D1FACBFC2", "vehicle_label": "6605"}, {"vehicle_update_ts": 1718233305, "lat": 40.051082611083984, "lon": -105.25033569335938, "trip": "114905974", "route_id": "205", "stop_id": "33698", "vehicle_id": "1A5C9CB693729B34E063DD4D1FACBFC2", "vehicle_label": "6607"}, {"vehicle_update_ts": 1718233323, "lat": 39.98405075073242, "lon": -105.25291442871094, "trip": "114905820", "route_id": "204", "stop_id": "19313", "vehicle_id": "1A5C9CB693769B34E063DD4D1FACBFC2", "vehicle_label": "6611"}, {"vehicle_update_ts": 1718233232, "lat": 40.016998291015625, "lon": -105.27690124511719, "trip": "114919250", "route_id": "DASH", "stop_id": "24591", "vehicle_id": "1A5C9CB6937A9B34E063DD4D1FACBFC2", "vehicle_label": "6615"}, {"vehicle_update_ts": 1718233302, "lat": 40.04724884033203, "lon": -105.27275085449219, "trip": "114905776", "route_id": "204", "stop_id": "12581", "vehicle_id": "1A5C9CB6937B9B34E063DD4D1FACBFC2", "vehicle_label": "6616"}, {"vehicle_update_ts": 1718233313, "lat": 40.051151275634766, "lon": -105.23258209228516, "trip": "114905991", "route_id": "205", "stop_id": "25662", "vehicle_id": "1A5C9CB6937E9B34E063DD4D1FACBFC2", "vehicle_label": "6621"}, {"vehicle_update_ts": 1718233323, "lat": 39.92826843261719, "lon": -105.0909652709961, "trip": "114915015", "route_id": "LD3", "stop_id": "17973", "vehicle_id": "1A5C9CB693809B34E063DD4D1FACBFC2", "vehicle_label": "6618"}, {"vehicle_update_ts": 1718233322, "lat": 40.00725173950195, "lon": -105.2533187866211, "trip": "114913989", "route_id": "BOND", "stop_id": "25465", "vehicle_id": "1A5C9CB693819B34E063DD4D1FACBFC2", "vehicle_label": "6619"}, {"vehicle_update_ts": 1718233324, "lat": 40.037532806396484, "lon": -105.25511932373047, "trip": "114914068", "route_id": "BOND", "stop_id": "19692", "vehicle_id": "1A5C9CB693829B34E063DD4D1FACBFC2", "vehicle_label": "6623"}, {"vehicle_update_ts": 1718233322, "lat": 39.98623275756836, "lon": -105.14225006103516, "trip": "114919251", "route_id": "DASH", "stop_id": "17887", "vehicle_id": "1A5C9CB693869B34E063DD4D1FACBFC2", "vehicle_label": "6627"}, {"vehicle_update_ts": 1718233326, "lat": 40.01453399658203, "lon": -105.177734375, "trip": "114918928", "route_id": "JUMP", "stop_id": "17862", "vehicle_id": "1A5C9CB693899B34E063DD4D1FACBFC2", "vehicle_label": "6630"}, {"vehicle_update_ts": 1718233322, "lat": 39.985782623291016, "lon": -105.22364807128906, "trip": "114919216", "route_id": "DASH", "stop_id": "21708", "vehicle_id": "1A5C9CB6938A9B34E063DD4D1FACBFC2", "vehicle_label": "6631"}, {"vehicle_update_ts": 1718233108, "lat": 40.01726531982422, "lon": -105.27687072753906, "trip": "114918953", "route_id": "JUMP", "stop_id": "33236", "vehicle_id": "1A5C9CB6938E9B34E063DD4D1FACBFC2", "vehicle_label": "6635"}, {"vehicle_update_ts": 1718233326, "lat": 40.025882720947266, "lon": -105.2726821899414, "trip": "114905852", "route_id": "204", "stop_id": "10364", "vehicle_id": "1A5C9CB693909B34E063DD4D1FACBFC2", "vehicle_label": "6637"}, {"vehicle_update_ts": 1718233322, "lat": 40.0174674987793, "lon": -105.22823333740234, "trip": "114906073", "route_id": "208", "stop_id": "22085", "vehicle_id": "1A5C9CB693919B34E063DD4D1FACBFC2", "vehicle_label": "6638"}, {"vehicle_update_ts": 1718233313, "lat": 39.71106719970703, "lon": -104.97623443603516, "trip": "114907012", "route_id": "3", "stop_id": "11981", "vehicle_id": "1A5C9CB693939B34E063DD4D1FACBFC2", "vehicle_label": "6640"}, {"vehicle_update_ts": 1718233311, "lat": 39.75571823120117, "lon": -104.84696960449219, "trip": "114902660", "route_id": "121", "stop_id": "15898", "vehicle_id": "1A5C9CB693949B34E063DD4D1FACBFC2", "vehicle_label": "6641"}, {"vehicle_update_ts": 1718233317, "lat": 39.72700119018555, "lon": -104.99026489257812, "trip": "114910659", "route_id": "52", "stop_id": "12327", "vehicle_id": "1A5C9CB693959B34E063DD4D1FACBFC2", "vehicle_label": "6642"}, {"vehicle_update_ts": 1718233319, "lat": 39.76945114135742, "lon": -105.02896881103516, "trip": "114908374", "route_id": "38", "stop_id": "11001", "vehicle_id": "1A5C9CB693979B34E063DD4D1FACBFC2", "vehicle_label": "6644"}, {"vehicle_update_ts": 1718233319, "lat": 39.770599365234375, "lon": -104.9223861694336, "trip": "114908396", "route_id": "38", "stop_id": "24831", "vehicle_id": "1A5C9CB693989B34E063DD4D1FACBFC2", "vehicle_label": "6645"}, {"vehicle_update_ts": 1718233312, "lat": 39.70796585083008, "lon": -104.8193359375, "trip": "114907010", "route_id": "3", "stop_id": "26335", "vehicle_id": "1A5C9CB693999B34E063DD4D1FACBFC2", "vehicle_label": "6646"}, {"vehicle_update_ts": 1718233319, "lat": 39.65385055541992, "lon": -105.0811996459961, "trip": "114911804", "route_id": "76", "stop_id": "17056", "vehicle_id": "1A5C9CB6939A9B34E063DD4D1FACBFC2", "vehicle_label": "6647"}, {"vehicle_update_ts": 1718233311, "lat": 39.735084533691406, "lon": -104.94888305664062, "trip": "114896598", "route_id": "10", "stop_id": "10181", "vehicle_id": "1A5C9CB6939C9B34E063DD4D1FACBFC2", "vehicle_label": "6649"}, {"vehicle_update_ts": 1718233312, "lat": 39.736717224121094, "lon": -104.99024963378906, "trip": "114910697", "route_id": "52", "stop_id": "12738", "vehicle_id": "1A5C9CB6939D9B34E063DD4D1FACBFC2", "vehicle_label": "6650"}, {"vehicle_update_ts": 1718233298, "lat": 39.722232818603516, "lon": -105.08136749267578, "trip": "114911809", "route_id": "76", "stop_id": "22917", "vehicle_id": "1A5C9CB6939E9B34E063DD4D1FACBFC2", "vehicle_label": "6651"}, {"vehicle_update_ts": 1718233311, "lat": 39.80461883544922, "lon": -105.10639953613281, "trip": "114911457", "route_id": "72", "stop_id": "14568", "vehicle_id": "1A5C9CB6939F9B34E063DD4D1FACBFC2", "vehicle_label": "6652"}, {"vehicle_update_ts": 1718233306, "lat": 39.71123123168945, "lon": -105.05258178710938, "trip": "114907016", "route_id": "3", "stop_id": "12085", "vehicle_id": "1A5C9CB693A19B34E063DD4D1FACBFC2", "vehicle_label": "6654"}, {"vehicle_update_ts": 1718233319, "lat": 39.696800231933594, "lon": -105.0121841430664, "trip": "114903397", "route_id": "14", "stop_id": "15462", "vehicle_id": "1A5C9CB693A39B34E063DD4D1FACBFC2", "vehicle_label": "6656"}, {"vehicle_update_ts": 1718233301, "lat": 39.788299560546875, "lon": -105.13417053222656, "trip": "", "route_id": "", "stop_id": "", "vehicle_id": "1A5C9CB693A49B34E063DD4D1FACBFC2", "vehicle_label": "6657"}, {"vehicle_update_ts": 1718233307, "lat": 39.80178451538086, "lon": -105.07666778564453, "trip": "114911841", "route_id": "76", "stop_id": "20821", "vehicle_id": "1A5C9CB693A79B34E063DD4D1FACBFC2", "vehicle_label": "6660"}, {"vehicle_update_ts": 1718233164, "lat": 39.825584411621094, "lon": -104.94255065917969, "trip": "114912440", "route_id": "88L", "stop_id": "25065", "vehicle_id": "1A5C9CB693A99B34E063DD4D1FACBFC2", "vehicle_label": "6662"}, {"vehicle_update_ts": 1718233319, "lat": 39.71813201904297, "lon": -105.12753295898438, "trip": "114907042", "route_id": "3", "stop_id": "16773", "vehicle_id": "1A5C9CB693AA9B34E063DD4D1FACBFC2", "vehicle_label": "6663"}, {"vehicle_update_ts": 1718233311, "lat": 39.70759963989258, "lon": -105.08480072021484, "trip": "114903387", "route_id": "14", "stop_id": "24858", "vehicle_id": "1A5C9CB693AB9B34E063DD4D1FACBFC2", "vehicle_label": "6664"}, {"vehicle_update_ts": 1718233315, "lat": 39.64070129394531, "lon": -104.90553283691406, "trip": "114911109", "route_id": "65", "stop_id": "16101", "vehicle_id": "1A5C9CB693AC9B34E063DD4D1FACBFC2", "vehicle_label": "6665"}, {"vehicle_update_ts": 1718233308, "lat": 39.76926803588867, "lon": -105.05284881591797, "trip": "114908353", "route_id": "38", "stop_id": "11060", "vehicle_id": "1A5C9CB693AE9B34E063DD4D1FACBFC2", "vehicle_label": "6667"}, {"vehicle_update_ts": 1718233311, "lat": 39.654232025146484, "lon": -104.99351501464844, "trip": "114910531", "route_id": "51", "stop_id": "13514", "vehicle_id": "1A5C9CB693B09B34E063DD4D1FACBFC2", "vehicle_label": "6669"}, {"vehicle_update_ts": 1718233311, "lat": 39.74760055541992, "lon": -105.0031509399414, "trip": "114910942", "route_id": "6", "stop_id": "21374", "vehicle_id": "1A5C9CB693B19B34E063DD4D1FACBFC2", "vehicle_label": "6670"}, {"vehicle_update_ts": 1718233317, "lat": 39.78108215332031, "lon": -104.9581298828125, "trip": "114909647", "route_id": "44", "stop_id": "13147", "vehicle_id": "1A5C9CB693B29B34E063DD4D1FACBFC2", "vehicle_label": "6671"}, {"vehicle_update_ts": 1718233311, "lat": 39.913818359375, "lon": -105.00354766845703, "trip": "114902066", "route_id": "120", "stop_id": "26108", "vehicle_id": "1A5C9CB693B39B34E063DD4D1FACBFC2", "vehicle_label": "6672"}, {"vehicle_update_ts": 1718233289, "lat": 39.74155044555664, "lon": -104.98590087890625, "trip": "", "route_id": "", "stop_id": "", "vehicle_id": "1A5C9CB693B49B34E063DD4D1FACBFC2", "vehicle_label": "6673"}, {"vehicle_update_ts": 1718233301, "lat": 39.74121856689453, "lon": -104.9864501953125, "trip": "114905543", "route_id": "19", "stop_id": "35033", "vehicle_id": "1A5C9CB693B59B34E063DD4D1FACBFC2", "vehicle_label": "6674"}, {"vehicle_update_ts": 1718233309, "lat": 39.76936721801758, "lon": -104.97308349609375, "trip": "114911374", "route_id": "7", "stop_id": "34787", "vehicle_id": "1A5C9CB693B69B34E063DD4D1FACBFC2", "vehicle_label": "6675"}, {"vehicle_update_ts": 1718233299, "lat": 39.78748321533203, "lon": -104.986083984375, "trip": "114911916", "route_id": "8", "stop_id": "11357", "vehicle_id": "1A5C9CB693B89B34E063DD4D1FACBFC2", "vehicle_label": "6677"}, {"vehicle_update_ts": 1718233326, "lat": 39.8089485168457, "lon": -104.97823333740234, "trip": "114911414", "route_id": "7", "stop_id": "17186", "vehicle_id": "1A5C9CB693B99B34E063DD4D1FACBFC2", "vehicle_label": "6678"}, {"vehicle_update_ts": 1718233305, "lat": 39.725582122802734, "lon": -104.85051727294922, "trip": "114910947", "route_id": "6", "stop_id": "15912", "vehicle_id": "1A5C9CB693BB9B34E063DD4D1FACBFC2", "vehicle_label": "6680"}, {"vehicle_update_ts": 1718233302, "lat": 39.75104904174805, "lon": -105.0022964477539, "trip": "114896599", "route_id": "10", "stop_id": "17766", "vehicle_id": "1A5C9CB693BC9B34E063DD4D1FACBFC2", "vehicle_label": "6681"}, {"vehicle_update_ts": 1718233299, "lat": 39.8786506652832, "lon": -105.00616455078125, "trip": "114905542", "route_id": "19", "stop_id": "10007", "vehicle_id": "1A5C9CB693BD9B34E063DD4D1FACBFC2", "vehicle_label": "6682"}, {"vehicle_update_ts": 1718233322, "lat": 39.73664855957031, "lon": -104.94059753417969, "trip": "114908709", "route_id": "40", "stop_id": "13050", "vehicle_id": "1A5C9CB693BF9B34E063DD4D1FACBFC2", "vehicle_label": "6684"}, {"vehicle_update_ts": 1718233318, "lat": 39.77296829223633, "lon": -104.94149780273438, "trip": "114908712", "route_id": "40", "stop_id": "34480", "vehicle_id": "1A5C9CB693C09B34E063DD4D1FACBFC2", "vehicle_label": "6685"}, {"vehicle_update_ts": 1718233322, "lat": 39.85653305053711, "lon": -105.00611877441406, "trip": "114905557", "route_id": "19", "stop_id": "21996", "vehicle_id": "1A5C9CB693C29B34E063DD4D1FACBFC2", "vehicle_label": "6687"}, {"vehicle_update_ts": 1718233302, "lat": 39.65325164794922, "lon": -104.91856384277344, "trip": "114908719", "route_id": "40", "stop_id": "14155", "vehicle_id": "1A5C9CB693C49B34E063DD4D1FACBFC2", "vehicle_label": "6689"}, {"vehicle_update_ts": 1718233307, "lat": 39.78821563720703, "lon": -105.1327133178711, "trip": "114909649", "route_id": "44", "stop_id": "34515", "vehicle_id": "1A5C9CB693C89B34E063DD4D1FACBFC2", "vehicle_label": "6693"}, {"vehicle_update_ts": 1718233322, "lat": 39.85951614379883, "lon": -104.95252990722656, "trip": "114912617", "route_id": "92", "stop_id": "20829", "vehicle_id": "1A5C9CB693C99B34E063DD4D1FACBFC2", "vehicle_label": "6694"}, {"vehicle_update_ts": 1718233306, "lat": 39.75171661376953, "lon": -105.05316925048828, "trip": "114910496", "route_id": "51", "stop_id": "16461", "vehicle_id": "1A5C9CB693CA9B34E063DD4D1FACBFC2", "vehicle_label": "6695"}, {"vehicle_update_ts": 1718233316, "lat": 39.70823287963867, "lon": -104.94087982177734, "trip": "114908779", "route_id": "40", "stop_id": "21795", "vehicle_id": "1A5C9CB693CB9B34E063DD4D1FACBFC2", "vehicle_label": "6696"}, {"vehicle_update_ts": 1718233322, "lat": 39.71818161010742, "lon": -104.97209930419922, "trip": "114912152", "route_id": "83D", "stop_id": "10480", "vehicle_id": "1A5C9CB693CF9B34E063DD4D1FACBFC2", "vehicle_label": "9303"}, {"vehicle_update_ts": 1718233324, "lat": 39.71061706542969, "lon": -104.81966400146484, "trip": "114904513", "route_id": "15L", "stop_id": "16378", "vehicle_id": "1A5C9CB693D29B34E063DD4D1FACBFC2", "vehicle_label": "9306"}, {"vehicle_update_ts": 1718233320, "lat": 39.74026870727539, "lon": -104.90381622314453, "trip": "114904548", "route_id": "15L", "stop_id": "12964", "vehicle_id": "1A5C9CB693D39B34E063DD4D1FACBFC2", "vehicle_label": "9307"}, {"vehicle_update_ts": 1718233299, "lat": 39.709434509277344, "lon": -104.93285369873047, "trip": "114912119", "route_id": "83L", "stop_id": "18865", "vehicle_id": "1A5C9CB693D49B34E063DD4D1FACBFC2", "vehicle_label": "9308"}, {"vehicle_update_ts": 1718233322, "lat": 39.626468658447266, "lon": -104.79219818115234, "trip": "114905184", "route_id": "169L", "stop_id": "18303", "vehicle_id": "1A5C9CB693D59B34E063DD4D1FACBFC2", "vehicle_label": "9309"}, {"vehicle_update_ts": 1718233309, "lat": 39.74026870727539, "lon": -104.95709991455078, "trip": "114904541", "route_id": "15L", "stop_id": "12913", "vehicle_id": "1A5C9CB693D79B34E063DD4D1FACBFC2", "vehicle_label": "9311"}, {"vehicle_update_ts": 1718233326, "lat": 39.67369842529297, "lon": -104.8697509765625, "trip": "114912118", "route_id": "83L", "stop_id": "15777", "vehicle_id": "1A5C9CB693D89B34E063DD4D1FACBFC2", "vehicle_label": "9312"}, {"vehicle_update_ts": 1718233303, "lat": 39.70598220825195, "lon": -104.91864776611328, "trip": "114912197", "route_id": "83D", "stop_id": "21420", "vehicle_id": "1A5C9CB693D99B34E063DD4D1FACBFC2", "vehicle_label": "9313"}, {"vehicle_update_ts": 1718233316, "lat": 39.73994827270508, "lon": -104.97360229492188, "trip": "114904460", "route_id": "15L", "stop_id": "12870", "vehicle_id": "1A5C9CB693DB9B34E063DD4D1FACBFC2", "vehicle_label": "9315"}, {"vehicle_update_ts": 1718233299, "lat": 39.727718353271484, "lon": -104.98605346679688, "trip": "114912169", "route_id": "83L", "stop_id": "14965", "vehicle_id": "1A5C9CB693DD9B34E063DD4D1FACBFC2", "vehicle_label": "9317"}, {"vehicle_update_ts": 1718233297, "lat": 39.7369499206543, "lon": -104.82323455810547, "trip": "", "route_id": "", "stop_id": "", "vehicle_id": "1A5C9CB693DE9B34E063DD4D1FACBFC2", "vehicle_label": "9318"}, {"vehicle_update_ts": 1718233322, "lat": 39.726318359375, "lon": -104.81763458251953, "trip": "114904521", "route_id": "15L", "stop_id": "21713", "vehicle_id": "1A5C9CB693DF9B34E063DD4D1FACBFC2", "vehicle_label": "9319"}, {"vehicle_update_ts": 1718233297, "lat": 39.745731353759766, "lon": -104.99051666259766, "trip": "114904491", "route_id": "15L", "stop_id": "17711", "vehicle_id": "1A5C9CB693E69B34E063DD4D1FACBFC2", "vehicle_label": "9326"}, {"vehicle_update_ts": 1718233318, "lat": 39.701351165771484, "lon": -104.9894027709961, "trip": "114896315", "route_id": "0L", "stop_id": "26274", "vehicle_id": "1A5C9CB693E79B34E063DD4D1FACBFC2", "vehicle_label": "9327"}, {"vehicle_update_ts": 1718233262, "lat": 39.74003219604492, "lon": -104.98197937011719, "trip": "114904574", "route_id": "15L", "stop_id": "21375", "vehicle_id": "1A5C9CB693E89B34E063DD4D1FACBFC2", "vehicle_label": "9328"}, {"vehicle_update_ts": 1718233319, "lat": 39.740081787109375, "lon": -104.82611846923828, "trip": "114904470", "route_id": "15L", "stop_id": "12847", "vehicle_id": "1A5C9CB693EC9B34E063DD4D1FACBFC2", "vehicle_label": "9332"}, {"vehicle_update_ts": 1718233312, "lat": 39.72626876831055, "lon": -104.98615264892578, "trip": "114896216", "route_id": "0", "stop_id": "14978", "vehicle_id": "1A5C9CB693ED9B34E063DD4D1FACBFC2", "vehicle_label": "9333"}, {"vehicle_update_ts": 1718233323, "lat": 0.0, "lon": 0.0, "trip": "114896187", "route_id": "0", "stop_id": "12529", "vehicle_id": "1A5C9CB693F29B34E063DD4D1FACBFC2", "vehicle_label": "9338"}, {"vehicle_update_ts": 1718233323, "lat": 39.67473220825195, "lon": -104.98766326904297, "trip": "114896289", "route_id": "0", "stop_id": "12536", "vehicle_id": "1A5C9CB693F99B34E063DD4D1FACBFC2", "vehicle_label": "9345"}, {"vehicle_update_ts": 1718233323, "lat": 39.5577507019043, "lon": -104.99708557128906, "trip": "114896210", "route_id": "0", "stop_id": "25676", "vehicle_id": "1A5C9CB693FA9B34E063DD4D1FACBFC2", "vehicle_label": "9346"}, {"vehicle_update_ts": 1718233293, "lat": 39.54724884033203, "lon": -104.99763488769531, "trip": "114896258", "route_id": "0", "stop_id": "26262", "vehicle_id": "1A5C9CB693FE9B34E063DD4D1FACBFC2", "vehicle_label": "9350"}, {"vehicle_update_ts": 1718233315, "lat": 39.72548294067383, "lon": -104.98619842529297, "trip": "114922277", "route_id": "0L", "stop_id": "14978", "vehicle_id": "1A5C9CB694079B34E063DD4D1FACBFC2", "vehicle_label": "9359"}, {"vehicle_update_ts": 1718233301, "lat": 39.74956512451172, "lon": -104.99551391601562, "trip": "114896278", "route_id": "0", "stop_id": "17715", "vehicle_id": "1A5C9CB6940A9B34E063DD4D1FACBFC2", "vehicle_label": "9362"}, {"vehicle_update_ts": 1718233322, "lat": 39.68709945678711, "lon": -104.98743438720703, "trip": "114896220", "route_id": "0", "stop_id": "12537", "vehicle_id": "1A5C9CB6940D9B34E063DD4D1FACBFC2", "vehicle_label": "9365"}, {"vehicle_update_ts": 1718232913, "lat": 39.754268646240234, "lon": -105.00133514404297, "trip": "114896200", "route_id": "0", "stop_id": "34326", "vehicle_id": "1A5C9CB6940E9B34E063DD4D1FACBFC2", "vehicle_label": "9366"}, {"vehicle_update_ts": 1718233319, "lat": 39.73998260498047, "lon": -104.97882080078125, "trip": "114904520", "route_id": "15L", "stop_id": "12870", "vehicle_id": "1A5C9CB694149B34E063DD4D1FACBFC2", "vehicle_label": "9372"}, {"vehicle_update_ts": 1718233322, "lat": 39.689334869384766, "lon": -104.90229797363281, "trip": "114912150", "route_id": "83D", "stop_id": "19842", "vehicle_id": "1A5C9CB694159B34E063DD4D1FACBFC2", "vehicle_label": "9373"}, {"vehicle_update_ts": 1718233319, "lat": 39.744384765625, "lon": -105.01028442382812, "trip": "114904452", "route_id": "15L", "stop_id": "25416", "vehicle_id": "1A5C9CB694179B34E063DD4D1FACBFC2", "vehicle_label": "9375"}, {"vehicle_update_ts": 1718233322, "lat": 39.74024963378906, "lon": -104.86356353759766, "trip": "114904576", "route_id": "15L", "stop_id": "12895", "vehicle_id": "1A5C9CB694199B34E063DD4D1FACBFC2", "vehicle_label": "9377"}, {"vehicle_update_ts": 1718233305, "lat": 39.73796844482422, "lon": -105.01602935791016, "trip": "", "route_id": "", "stop_id": "", "vehicle_id": "1A5C9CB6941A9B34E063DD4D1FACBFC2", "vehicle_label": "9378"}, {"vehicle_update_ts": 1718233308, "lat": 39.68936538696289, "lon": -104.8798828125, "trip": "114912170", "route_id": "83L", "stop_id": "21248", "vehicle_id": "1A5C9CB6941E9B34E063DD4D1FACBFC2", "vehicle_label": "9382"}, {"vehicle_update_ts": 1718233158, "lat": 39.737815856933594, "lon": -104.82354736328125, "trip": "", "route_id": "", "stop_id": "", "vehicle_id": "1A5C9CB694209B34E063DD4D1FACBFC2", "vehicle_label": "9384"}, {"vehicle_update_ts": 1718233322, "lat": 39.74005126953125, "lon": -104.88638305664062, "trip": "114904509", "route_id": "15L", "stop_id": "13020", "vehicle_id": "1A5C9CB694249B34E063DD4D1FACBFC2", "vehicle_label": "9388"}, {"vehicle_update_ts": 1718233300, "lat": 39.741416931152344, "lon": -104.98961639404297, "trip": "114896152", "route_id": "0", "stop_id": "17701", "vehicle_id": "1A5C9CB694279B34E063DD4D1FACBFC2", "vehicle_label": "9391"}, {"vehicle_update_ts": 1718233301, "lat": 39.85546875, "lon": -104.9874496459961, "trip": "114902281", "route_id": "120X", "stop_id": "18681", "vehicle_id": "1A5C9CB694299B34E063DD4D1FACBFC2", "vehicle_label": "9393"}, {"vehicle_update_ts": 1718233299, "lat": 39.69413375854492, "lon": -104.98756408691406, "trip": "114896262", "route_id": "0", "stop_id": "12556", "vehicle_id": "1A5C9CB6942A9B34E063DD4D1FACBFC2", "vehicle_label": "9394"}, {"vehicle_update_ts": 1718233316, "lat": 39.616233825683594, "lon": -104.9881820678711, "trip": "114896233", "route_id": "0", "stop_id": "12553", "vehicle_id": "1A5C9CB6942B9B34E063DD4D1FACBFC2", "vehicle_label": "9395"}, {"vehicle_update_ts": 1718233319, "lat": 39.755184173583984, "lon": -105.00033569335938, "trip": "114902312", "route_id": "120X", "stop_id": "34344", "vehicle_id": "1A5C9CB6942C9B34E063DD4D1FACBFC2", "vehicle_label": "9396"}, {"vehicle_update_ts": 1718233316, "lat": 39.754417419433594, "lon": -105.0009536743164, "trip": "114896248", "route_id": "0", "stop_id": "20745", "vehicle_id": "1A5C9CB6942D9B34E063DD4D1FACBFC2", "vehicle_label": "9397"}, {"vehicle_update_ts": 1718233315, "lat": 39.84946823120117, "lon": -104.98548126220703, "trip": "114902254", "route_id": "120X", "stop_id": "21994", "vehicle_id": "1A5C9CB6942E9B34E063DD4D1FACBFC2", "vehicle_label": "9398"}, {"vehicle_update_ts": 1718233320, "lat": 39.749698638916016, "lon": -104.99576568603516, "trip": "114904435", "route_id": "15L", "stop_id": "17714", "vehicle_id": "1A5C9CB694309B34E063DD4D1FACBFC2", "vehicle_label": "9402"}, {"vehicle_update_ts": 1718233305, "lat": 39.7401008605957, "lon": -104.8474349975586, "trip": "114904516", "route_id": "15L", "stop_id": "12954", "vehicle_id": "1A5C9CB694329B34E063DD4D1FACBFC2", "vehicle_label": "9404"}, {"vehicle_update_ts": 1718233322, "lat": 39.711082458496094, "lon": -104.8420181274414, "trip": "114908398", "route_id": "3L", "stop_id": "12099", "vehicle_id": "1A5C9CB694349B34E063DD4D1FACBFC2", "vehicle_label": "9406"}, {"vehicle_update_ts": 1718233270, "lat": 39.61761474609375, "lon": -105.01232147216797, "trip": "115029583", "route_id": "101D", "stop_id": "25438", "vehicle_id": "1A9D1889800F674EE063DD4D1FACC172", "vehicle_label": "327,338,344"}, {"vehicle_update_ts": 1718233328, "lat": 39.66203308105469, "lon": -104.9972152709961, "trip": "115029432", "route_id": "101D", "stop_id": "24882", "vehicle_id": "1AA4B31A855F187BE063DD4D1FACC1AC", "vehicle_label": "212,218,251"}, {"vehicle_update_ts": 1718232927, "lat": 39.69979476928711, "lon": -104.9862289428711, "trip": "115029613", "route_id": "101H", "stop_id": "25982", "vehicle_id": "1AA4B31A85CB187BE063DD4D1FACC1AC", "vehicle_label": "246,257,291,301"}, {"vehicle_update_ts": 1718232382, "lat": 39.691368103027344, "lon": -104.82848358154297, "trip": "115029461", "route_id": "101H", "stop_id": "34578", "vehicle_id": "1AA69CAC2CDCA159E063DC4D1FAC2089", "vehicle_label": "222,229,311,347"}, {"vehicle_update_ts": 1718233297, "lat": 39.763187408447266, "lon": -104.84728240966797, "trip": "115029825", "route_id": "107R", "stop_id": "34745", "vehicle_id": "1AA763B450A274E0E063DC4D1FAC3F42", "vehicle_label": "273,286"}, {"vehicle_update_ts": 1718233263, "lat": 39.74352264404297, "lon": -105.01371765136719, "trip": "115029697", "route_id": "103W", "stop_id": "25429", "vehicle_id": "1AA9A5648F79BE4EE063DC4D1FAC1EB1", "vehicle_label": "101,121,142"}, {"vehicle_update_ts": 1718233244, "lat": 39.62053298950195, "lon": -104.90022277832031, "trip": "115029833", "route_id": "107R", "stop_id": "25983", "vehicle_id": "1AA9C41D19940222E063DD4D1FACA2DB", "vehicle_label": "305,306"}, {"vehicle_update_ts": 1718233343, "lat": 39.7256965637207, "lon": -105.1771011352539, "trip": "115029743", "route_id": "103W", "stop_id": "33568", "vehicle_id": "1AA9C41D19D10222E063DD4D1FACA2DB", "vehicle_label": "113,139,140"}, {"vehicle_update_ts": 1718233263, "lat": 39.74114227294922, "lon": -105.01046752929688, "trip": "115029462", "route_id": "101H", "stop_id": "25427", "vehicle_id": "1AA9D05170F7BE71E063DC4D1FAC6896", "vehicle_label": "241,248,252,289"}, {"vehicle_update_ts": 1718233347, "lat": 39.72182083129883, "lon": -105.1306381225586, "trip": "115029695", "route_id": "103W", "stop_id": "33955", "vehicle_id": "1AAA5C4561532660E063DC4D1FAC32F3", "vehicle_label": "243,263,284"}, {"vehicle_update_ts": 1718233309, "lat": 39.740169525146484, "lon": -105.00732421875, "trip": "115029401", "route_id": "101D", "stop_id": "25427", "vehicle_id": "1AAA5C4561B12660E063DC4D1FAC32F3", "vehicle_label": "239,253,258"}, {"vehicle_update_ts": 1718233340, "lat": 39.73657989501953, "lon": -105.09990692138672, "trip": "115029740", "route_id": "103W", "stop_id": "33565", "vehicle_id": "1AAB0592B9A61BA5E063DC4D1FAC96EF", "vehicle_label": "110,116,133"}, {"vehicle_update_ts": 1718233196, "lat": 39.77033233642578, "lon": -104.97427368164062, "trip": "114913062", "route_id": "A", "stop_id": "34667", "vehicle_id": "1AAE948BC4E32CDCE063DD4D1FAC2DF5", "vehicle_label": "4009,4010,4035,4036"}, {"vehicle_update_ts": 1718233204, "lat": 39.8382682800293, "lon": -104.68187713623047, "trip": "114913061", "route_id": "A", "stop_id": "34606", "vehicle_id": "1AAF3575B97A0BC4E063DD4D1FAC8076", "vehicle_label": "4021,4022,4059,4060"}, {"vehicle_update_ts": 1718232842, "lat": 39.792320251464844, "lon": -105.11278533935547, "trip": "114901097", "route_id": "113G", "stop_id": "34510", "vehicle_id": "1AAF4AE73C936287E063DD4D1FAC32AC", "vehicle_label": "4061,4062"}, {"vehicle_update_ts": 1718232965, "lat": 39.80736541748047, "lon": -104.78400421142578, "trip": "114913007", "route_id": "A", "stop_id": "34475", "vehicle_id": "1AAFA0BCF1873C9BE063DD4D1FAC4463", "vehicle_label": "4031,4032,4063,4064"}, {"vehicle_update_ts": 1718233193, "lat": 39.75394058227539, "lon": -105.00065612792969, "trip": "114901098", "route_id": "113G", "stop_id": "34781", "vehicle_id": "1AAFB62F2D5A910DE063DD4D1FACF91C", "vehicle_label": "4049,4050"}, {"vehicle_update_ts": 1718233213, "lat": 39.769954681396484, "lon": -104.88261413574219, "trip": "114912957", "route_id": "A", "stop_id": "34471", "vehicle_id": "1AAFD66083546703E063DD4D1FACEA37", "vehicle_label": "4025,4026,4053,4054"}, {"vehicle_update_ts": 1718233211, "lat": 39.799869537353516, "lon": -104.9543685913086, "trip": "114901562", "route_id": "117N", "stop_id": "35246", "vehicle_id": "1AB004D852D85A49E063DD4D1FACC01B", "vehicle_label": "4055,4056"}, {"vehicle_update_ts": 1718233206, "lat": 39.7545166015625, "lon": -104.99922943115234, "trip": "114913006", "route_id": "A", "stop_id": "34465", "vehicle_id": "1AB00C03FD2A7DE3E063DD4D1FAC405C", "vehicle_label": "4003,4004,4033,4034"}, {"vehicle_update_ts": 1718233238, "lat": 39.79658508300781, "lon": -105.09043884277344, "trip": "114901064", "route_id": "113G", "stop_id": "34541", "vehicle_id": "1AB01A216B7CDD79E063DD4D1FAC22AD", "vehicle_label": "4007,4008"}, {"vehicle_update_ts": 1718232830, "lat": 39.902950286865234, "lon": -104.96012878417969, "trip": "114901534", "route_id": "117N", "stop_id": "35257", "vehicle_id": "1AB073C92BE2AF55E063DD4D1FAC0AE2", "vehicle_label": "4039,4040"}, {"vehicle_update_ts": 1718233207, "lat": 39.75629806518555, "lon": -104.79400634765625, "trip": "114913091", "route_id": "A", "stop_id": "34472", "vehicle_id": "1AB077547D8FDF2AE063DD4D1FAC6984", "vehicle_label": "4041,4042,4047,4048"}, {"vehicle_update_ts": 1718232739, "lat": 39.77403259277344, "lon": -104.99698638916016, "trip": "114901035", "route_id": "113B", "stop_id": "34782", "vehicle_id": "1AB0DB7B10ECBCF1E063DD4D1FAC8C87", "vehicle_label": "4037,4038"}, {"vehicle_update_ts": 1718233204, "lat": 39.77227783203125, "lon": -104.98467254638672, "trip": "114901535", "route_id": "117N", "stop_id": "34668", "vehicle_id": "1AB0DB7B10F2BCF1E063DD4D1FAC8C87", "vehicle_label": "4029,4030"}, {"vehicle_update_ts": 1718232739, "lat": 39.76740264892578, "lon": -104.8511962890625, "trip": "115029866", "route_id": "107R", "stop_id": "34744", "vehicle_id": "1AB2D12E233B6F9EE063DD4D1FAC944B", "vehicle_label": "261"}, {"vehicle_update_ts": 1718233329, "lat": 39.754886627197266, "lon": -105.00341796875, "trip": "115029480", "route_id": "101E", "stop_id": "25430", "vehicle_id": "1AB4D8965557074FE063DD4D1FAC7F12", "vehicle_label": "1AB926167B478904E063DD4D1FACF325"}, {"vehicle_update_ts": 1718233148, "lat": 39.62078857421875, "lon": -104.90031433105469, "trip": "115029800", "route_id": "107R", "stop_id": "34010", "vehicle_id": "1AB55286E50AAE47E063DC4D1FACFB00", "vehicle_label": "277,313"}, {"vehicle_update_ts": 1718233287, "lat": 39.57844924926758, "lon": -104.87633514404297, "trip": "115029630", "route_id": "101E", "stop_id": "25988", "vehicle_id": "1AB5BD884DE1B418E063DC4D1FACCD1D", "vehicle_label": "324,328,331,346"}, {"vehicle_update_ts": 1718232827, "lat": 39.75325012207031, "lon": -105.00465393066406, "trip": "115029741", "route_id": "103W", "stop_id": "25433", "vehicle_id": "1AB844AB8F5A58C6E063DD4D1FAC6503", "vehicle_label": "102,109,144"}, {"vehicle_update_ts": 1718233347, "lat": 39.73664093017578, "lon": -105.06561279296875, "trip": "115029654", "route_id": "103W", "stop_id": "33967", "vehicle_id": "1AB8C65259867190E063DC4D1FAC536B", "vehicle_label": "101,114,115"}]